Workbook

Sheet Levantamento
A1: Código IBGE | B1: Região | C1: UF | D1: Município | E1: RIDE RM AU - IBGE 2024 | F1: RMs ENMU | G1: Área de Estudo ENMU | H1: Mapa do Turismo Brasileiro 2022 | I1: Mapa do Turismo Brasileiro 2024 | J1: Tipologia PNDU | K1: População - Censo 2010 | L1: Faixa Populacional - Censo 2010 | M1: População - Censo 2022 | N1: Faixa Populacional - Censo 2022 | O1: Estimativa populacional 2025 | P1: Faixa populacional - 2025 | Q1: Ofício | R1: Respondeu ao levantamento | S1: Possui Plano de Mobilidade Urbana | T1: Ano de elaboração | U1: Aprovado em lei ou ato normativo | V1: Instrumento Legal | W1: Nº da Lei | X1: Data da Lei | Y1: Link | Z1: Arquivo | AA1: Sistemas de Informação | AB1: Elaborando plano | AC1: Previsão de conclusão | AD1: Repondido por qual instrumento | AE1: Data da resposta | AF1: Fonte da Resposta | AG1: Obrigados Estimativa 2025 | AH1: Obrigados Censo 2022 - antigo | AI1: Obrigados Censo 2022 - atualizado
A2: 3550308 | B2: SE | C2: SP | D2: São Paulo | E2: RM de São Paulo (SP) | F2: Sim | G2: Sim | H2: A | I2: #N/A | J2: CD 1A | K2: 11253503 | L2: Mais de 1 milhão | M2: 11451999 | N2: Mais de 1 milhão | O2: 11904961 | P2: Mais de 1 milhão | Q2: Sim | R2: Sim | S2: Sim | T2: 2016 | U2: Sim | V2: Decreto Municipal | W2: 56.834/2016 | X2: 42424 | Y2: http://www.prefeitura.sp.gov.br/cidade/secretarias/transportes/planmob/ | Z2: \\londrina\SNTMU$\a. DEPARTAMENTOS\i. DEPLAN\2.CGARG\SIMU\Levantamento Planos de Mobilidade 2019\Planos Municipais - exemplos\SUDESTE\São Paulo\São Paulo_SP | AA2: https://www.prefeitura.sp.gov.br/cidade/secretarias/mobilidade/institucional/sptrans/acesso_a_informacao/index.php?p=295718; https://www.sptrans.com.br/terminais-corredores-e-pontos-de-parada; https://www.sptrans.com.br/desenvolvedores/ | AB2: Nao | AD2: Ofício nº 10/2016 | AE2: 42499 | AG2: Sim | AH2: Sim | AI2: Sim
A3: 3304557 | B3: SE | C3: RJ | D3: Rio de Janeiro | E3: RM do Rio de Janeiro (RJ) | F3: Sim | G3: Sim | H3: A | I3: A | J3: CD 1A | K3: 6320446 | L3: Mais de 1 milhão | M3: 6211223 | N3: Mais de 1 milhão | O3: 6730729 | P3: Mais de 1 milhão | Q3: Sim | R3: Sim | S3: Sim | T3: 2019 | U3: Sim | V3: Decreto Municipal | W3: 4.571/2019 | X3: 43558 | Y3: www.rio.rj.gov.br/web/pmus | Z3: \\Londrina\sntmu$\a. DEPARTAMENTOS\i. DEPLAN\2.CGARG\SIMU\Levantamento Planos de Mobilidade 2019\Planos Municipais - exemplos\SUDESTE\Rio de Janeiro\Rio de Janeiro_RJ | AA3: https://www.data.rio/search?groupIds=cbe84df2333a463b9d4e20aca5177936&sort=-modified | AB3: Nao | AD3: Ofício nº 21/2019 | AE3: 43570 | AF3: Pesquisa PlanMob 2019 | AG3: Sim | AH3: Sim | AI3: Sim
A4: 5300108 | B4: CO | C4: DF | D4: Brasília | E4: RIDE do Distrito Federal e Entorno | F4: Sim | G4: Sim | H4: A | I4: A | J4: CD 1A | K4: 2570160 | L4: Mais de 1 milhão | M4: 2817381 | N4: Mais de 1 milhão | O4: 2996899 | P4: Mais de 1 milhão | Q4: Sim | R4: Sim | S4: Sim | T4: 2011 | U4: Sim | V4: Lei Distrital | W4: 4.566/2011 | X4: 40667 | Y4: http://www.semob.df.gov.br/pdtu/ | Z4: \\Londrina\sntmu$\a. DEPARTAMENTOS\i. DEPLAN\2.CGARG\SIMU\Levantamento Planos de Mobilidade 2019\Planos Municipais - exemplos\CENTRO-OESTE\Brasília_DF | AA4: https://geoserver.semob.df.gov.br/geoserver/web/wicket/bookmarkable/org.geoserver.web.demo.MapPreviewPage?0&filter=false http://dados.df.gov.br/organization/d264c504-23b4-40fd-afb2-1ec81912f943?groups=mobilidade | AB4: Nao | AD4: Pemob/2019 | AG4: Sim | AH4: Sim | AI4: Sim
A5: 2304400 | B5: NE | C5: CE | D5: Fortaleza | E5: RM de Fortaleza (CE) | F5: Sim | G5: Sim | H5: A | I5: A | J5: CD 1A | K5: 2452185 | L5: Mais de 1 milhão | M5: 2428708 | N5: Mais de 1 milhão | O5: 2578483 | P5: Mais de 1 milhão | Q5: Sim | R5: Sim | S5: Sim | T5: 2023 | U5: Sim | V5: Lei Municipal | W5: 11390/2023 | X5: 45187 | Y5: https://sapl.fortaleza.ce.leg.br/norma/13698?display= https://fortaleza2040.fortaleza.ce.gov.br/site/assets/files/publications/fortaleza2040_plano_de_mobilidade_urbana_17-08-2015.pdf | Z5: \\Londrina\sntmu$\a. DEPARTAMENTOS\i. DEPLAN\2.CGARG\SIMU\Levantamento Planos de Mobilidade 2019\Planos Municipais - exemplos\NORDESTE\Fortaleza_CE | AA5: https://dados.fortaleza.ce.gov.br/dataset/?groups=transporte | AB5: Nao | AD5: Pemob 2025 | AE5: 45894 | AF5: Victor Macêdo Lacerda | AG5: Sim | AH5: Sim | AI5: Sim
A6: 2927408 | B6: NE | C6: BA | D6: Salvador | E6: RM de Salvador (BA) | F6: Sim | G6: Sim | H6: A | I6: A | J6: CD 1A | K6: 2675656 | L6: Mais de 1 milhão | M6: 2417678 | N6: Mais de 1 milhão | O6: 2564204 | P6: Mais de 1 milhão | Q6: Sim | R6: Sim | S6: Sim | T6: 2018 | U6: Sim | V6: Lei Municipal | W6: 9.374/2018 | X6: 43286 | Y6: http://www.planmob.salvador.ba.gov.br/ | Z6: \\Londrina\sntmu$\a. DEPARTAMENTOS\i. DEPLAN\2.CGARG\SIMU\Levantamento Planos de Mobilidade 2019\Planos Municipais - exemplos\NORDESTE\Salvador_BA | AA6: https://dados.salvador.ba.gov.br/search?tags=transito | AB6: Nao | AD6: Ofício nº 154/2017 | AE6: 43291 | AG6: Sim | AH6: Sim | AI6: Sim
A7: 3106200 | B7: SE | C7: MG | D7: Belo Horizonte | E7: RM de Belo Horizonte (MG) | F7: Sim | G7: Sim | H7: A | I7: A | J7: CD 1A | K7: 2375151 | L7: Mais de 1 milhão | M7: 2315560 | N7: Mais de 1 milhão | O7: 2415872 | P7: Mais de 1 milhão | Q7: Sim | R7: Sim | S7: Sim | T7: 2019 | U7: Sim | V7: Lei Municipal (Plano Diretor) | W7: 11.181/2019 | X7: 43685 | Y7: https://prefeitura.pbh.gov.br/politica-urbana/planejamento-urbano/plano-diretor/proposta | Z7: L:\a. DEPARTAMENTOS\i. DEPLAN\2.CGARG\SIMU\Levantamento Planos de Mobilidade 2019\Planos Municipais - exemplos\SUDESTE\Minas Gerais\Belo Horizonte_MG | AA7: https://dados.pbh.gov.br/organization/bhtrans | AB7: Nao | AD7: Pemob 2019 | AE7: 43840 | AG7: Sim | AH7: Sim | AI7: Sim
A8: 1302603 | B8: N | C8: AM | D8: Manaus | E8: RM de Manaus (AM) | F8: Sim | G8: Sim | H8: A | I8: A | J8: CD 1C | K8: 1802014 | L8: Mais de 1 milhão | M8: 2063689 | N8: Mais de 1 milhão | O8: 2303732 | P8: Mais de 1 milhão | Q8: Sim | R8: Sim | S8: Sim | T8: 2015 | U8: Sim | V8: Lei Complementar | W8: 2.075/2015 | X8: 42367 | Y8: http://transporte.manaus.am.gov.br/planmob/ | Z8: L:\a. DEPARTAMENTOS\i. DEPLAN\2.CGARG\SIMU\Levantamento Planos de Mobilidade 2019\Planos Municipais - exemplos\NORTE\Manaus_AM | AB8: Nao | AD8: Ofício nº 01/2016 Pemob 2024 | AE8: 42398 | AG8: Sim | AH8: Sim | AI8: Sim
A9: 4106902 | B9: S | C9: PR | D9: Curitiba | E9: RM de Curitiba (PR) | F9: Sim | G9: Sim | H9: A | I9: A | J9: CD 1A | K9: 1751907 | L9: Mais de 1 milhão | M9: 1773718 | N9: Mais de 1 milhão | O9: 1830795 | P9: Mais de 1 milhão | Q9: Sim | R9: Sim | S9: Sim | T9: 2022 | U9: Sim | V9: Decreto Municipal | W9: 485/2023 | X9: 45013 | Y9: https://ippuc.org.br/mostrarpagina.php?pagina=312&idioma=1&ampliar=não https://ippuc.org.br/storage/uploads/0a2076cd-5284-4183-8aed-9c12c0aa617b/PS-Mobilidade-VOL-1.pdf | Z9: L:\a. DEPARTAMENTOS\i. DEPLAN\2.CGARG\SIMU\Levantamento Planos de Mobilidade 2019\Planos Municipais - exemplos\SUL\Paraná\Curitiba_PR | AB9: Nao | AD9: Pemob 2024 | AF9: Pemob 2024 | AG9: Sim | AH9: Sim | AI9: Sim
A10: 2611606 | B10: NE | C10: PE | D10: Recife | E10: RM de Recife (PE) | F10: Sim | G10: Sim | H10: A | I10: A | J10: CD 1A | K10: 1537704 | L10: Mais de 1 milhão | M10: 1488920 | N10: Mais de 1 milhão | O10: 1588376 | P10: Mais de 1 milhão | Q10: Sim | R10: Sim | S10: Sim | T10: 2021 | U10: Sim | V10: Lei Municipal | W10: 18887/2021 | X10: 44559 | Z10: L:\a. DEPARTAMENTOS\i. DEPLAN\2.CGARG\SIMU\Levantamento Planos de Mobilidade 2019\Planos Municipais - exemplos\NORDESTE\Recife_PE | AA10: http://dados.recife.pe.gov.br/nl/dataset?tags=transporte https://www.granderecife.pe.gov.br/transporte/dados-e-estatisticas/passageiros/ | AB10: Nao | AD10: Email | AE10: 44770 | AF10: cttupresidencia@recife.pe.gov.br | AG10: Sim | AH10: Sim | AI10: Sim
A11: 5208707 | B11: CO | C11: GO | D11: Goiânia | E11: RM de Goiânia (GO) | F11: Sim | G11: Sim | H11: A | I11: A | J11: CD 1A | K11: 1302001 | L11: Mais de 1 milhão | M11: 1437366 | N11: Mais de 1 milhão | O11: 1503256 | P11: Mais de 1 milhão | Q11: Sim | R11: Sim | S11: Sim | T11: 2024 | U11: Sim | V11: Decreto Municipal | W11: 1350/2024 | X11: 45394 | Y11: https://www.goiania.go.gov.br/html/gabinete_civil/sileg/dados/legis/2024/dc_20240412_000001350.html | AB11: Nao | AD11: Pemob 2024 | AE11: 45478 | AG11: Sim | AH11: Sim | AI11: Sim
A12: 1501402 | B12: N | C12: PA | D12: Belém | E12: RM de Belém (PA) | F12: Sim | G12: Sim | H12: A | I12: A | J12: CD 1A | K12: 1393399 | L12: Mais de 1 milhão | M12: 1303403 | N12: Mais de 1 milhão | O12: 1397315 | P12: Mais de 1 milhão | Q12: Sim | R12: Sim | S12: Sim | T12: 2016 | U12: Sim | V12: Decreto Municipal | W12: 86.545/2016 | X12: 42626 | Y12: http://www.belem.pa.gov.br/diarioom/baixarDiario?idd=8117 | Z12: L:\a. DEPARTAMENTOS\i. DEPLAN\2.CGARG\SIMU\Levantamento Planos de Mobilidade 2019\Planos Municipais - exemplos\NORTE\Belém_PA | AB12: Nao | AG12: Sim | AH12: Sim | AI12: Sim
A13: 4314902 | B13: S | C13: RS | D13: Porto Alegre | E13: RM de Porto Alegre (RS) | F13: Sim | G13: Sim | H13: A | I13: A | J13: CD 1A | K13: 1409351 | L13: Mais de 1 milhão | M13: 1332833 | N13: Mais de 1 milhão | O13: 1388794 | P13: Mais de 1 milhão | Q13: Sim | R13: Sim | S13: Sim | T13: 2022 | U13: Sim | V13: Lei Complementar | W13: 951/2022 | X13: 44790 | Y13: https://prefeitura.poa.br/smim/projetos/plano-de-mobilidade-urbana | Z13: L:\a. DEPARTAMENTOS\i. DEPLAN\2.CGARG\SIMU\Levantamento Planos de Mobilidade 2019\Planos Municipais - exemplos\SUL\Rio Grande do Sul\Porto Alegre_RS | AA13: https://dadosabertos.poa.br/group/mobilidade | AB13: Nao | AD13: E-mail | AE13: 45645 | AF13: joaquim@portoalegre.rs.gov.br | AG13: Sim | AH13: Sim | AI13: Sim
A14: 3518800 | B14: SE | C14: SP | D14: Guarulhos | E14: RM de São Paulo (SP) | F14: Sim | G14: Sim | H14: B | I14: B | J14: CD 1A | K14: 1221979 | L14: Mais de 1 milhão | M14: 1291771 | N14: Mais de 1 milhão | O14: 1349100 | P14: Mais de 1 milhão | Q14: Sim | R14: Sim | S14: Sim | T14: 2019 | U14: Sim | V14: Decreto Municipal | W14: 35931/2019 | X14: 43615 | Y14: https://www.guarulhos.sp.gov.br/plano-de-mobilidade-urbana-de-guarulhos | Z14: L:\a. DEPARTAMENTOS\i. DEPLAN\2.CGARG\SIMU\Levantamento Planos de Mobilidade\Planos Municipais - exemplos\SUDESTE\São Paulo\Guarulhos | AB14: Nao | AD14: Pemob/2019 | AG14: Sim | AH14: Sim | AI14: Sim
A15: 3509502 | B15: SE | C15: SP | D15: Campinas | E15: RM de Campinas (SP) | F15: Sim | G15: Sim | H15: A | I15: A | J15: CD 1A | K15: 1080113 | L15: Mais de 1 milhão | M15: 1139047 | N15: Mais de 1 milhão | O15: 1187974 | P15: Mais de 1 milhão | Q15: Sim | R15: Sim | S15: Sim | T15: 2019 | U15: Sim | V15: Decreto Municipal | W15: 20.571/2019 | X15: 43782 | Y15: https://bibliotecajuridica.campinas.sp.gov.br/index/visualizaroriginal/id/134989 | Z15: \\londrina\SNTMU$\a. DEPARTAMENTOS\i. DEPLAN\2.CGARG\SIMU\Levantamento Planos de Mobilidade 2019\Planos Municipais - exemplos\SUDESTE\São Paulo\Campinas_SP | AB15: Nao | AD15: Pemob/2019 | AG15: Sim | AH15: Sim | AI15: Sim
A16: 2111300 | B16: NE | C16: MA | D16: São Luís | E16: RM da Grande São Luís (MA) | F16: Sim | G16: Sim | H16: A | I16: A | J16: CD 1A | K16: 1014837 | L16: Mais de 1 milhão | M16: 1037775 | N16: Mais de 1 milhão | O16: 1089215 | P16: Mais de 1 milhão | Q16: Sim | R16: Sim | S16: Sim | T16: 2017 | U16: Sim | V16: Lei Municipal | W16: 6.292/2017 | X16: 43097 | Z16: L:\a. DEPARTAMENTOS\i. DEPLAN\2.CGARG\SIMU\Levantamento Planos de Mobilidade 2019\Planos Municipais - exemplos\NORDESTE\São Luís_MA | AB16: Nao | AD16: Ofício nº 21/2019 | AE16: 43549 | AF16: Pesquisa PlanMob 2019 | AG16: Sim | AH16: Sim | AI16: Sim
A17: 2704302 | B17: NE | C17: AL | D17: Maceió | E17: RM de Maceió (AL) | F17: Sim | G17: Sim | H17: A | I17: #N/A | J17: CD 1A | K17: 932748 | L17: De 500 mil a 1 milhão | M17: 957916 | N17: De 500 mil a 1 milhão | O17: 994952 | P17: De 500 mil a 1 milhão | Q17: Sim | R17: Sim | S17: Nao | U17: Nao possui plano | V17: Nao possui plano | X17: Nao possui plano | AB17: Sim | AC17: Sem previsao | AD17: Email | AE17: 44839 | AF17: chefiadegabinetesmtt@gmail.com | AG17: Sim | AH17: Sim | AI17: Sim
A18: 5002704 | B18: CO | C18: MS | D18: Campo Grande | E18: #N/A | F18: Não | G18: Nao | H18: A | I18: A | J18: CD 1C | K18: 786797 | L18: De 500 mil a 1 milhão | M18: 898100 | N18: De 500 mil a 1 milhão | O18: 962883 | P18: De 500 mil a 1 milhão | Q18: Sim | R18: Sim | S18: Sim | T18: 2024 | U18: Sim | V18: Lei Municipal | W18: 7282/2024 | X18: 45488 | Y18: http://www.pmcg.ms.gov.br/egov/downloadFile.php?id=11400&fileField=arquivo_dow&table=downloads&key=id_dow&sigla_sec=planurb https://www.campogrande.ms.gov.br/planurb/consulte-2/ | Z18: \\Londrina\sntmu$\a. DEPARTAMENTOS\i. DEPLAN\2.CGARG\SIMU\Levantamento Planos de Mobilidade 2019\Planos Municipais - exemplos\CENTRO-OESTE\Campo Grande_MS | AB18: Nao | AD18: Pemob 2024 | AE18: 45499 | AG18: Sim | AH18: Sim | AI18: Sim
A19: 3304904 | B19: SE | C19: RJ | D19: São Gonçalo | E19: RM do Rio de Janeiro (RJ) | F19: Sim | G19: Sim | H19: C | I19: #N/A | J19: CD 1A | K19: 999728 | L19: De 500 mil a 1 milhão | M19: 896744 | N19: De 500 mil a 1 milhão | O19: 960196 | P19: De 500 mil a 1 milhão | Q19: Sim | R19: Sim | S19: Sim | T19: 2024 | U19: Sim | V19: Lei Municipal | W19: 1529/2024 | X19: 45401 | AB19: Nao | AD19: Email | AE19: 45912 | AF19: apolotardin@gmail.com | AG19: Sim | AH19: Sim | AI19: Sim
A20: 2211001 | B20: NE | C20: PI | D20: Teresina | E20: RIDE da Grande Teresina (PI/MA) | F20: Sim | G20: Sim | H20: A | I20: A | J20: CD 1A | K20: 814230 | L20: De 500 mil a 1 milhão | M20: 866300 | N20: De 500 mil a 1 milhão | O20: 905692 | P20: De 500 mil a 1 milhão | Q20: Sim | R20: Sim | S20: Sim | T20: 2022 | U20: Nao | V20: Nao aprovado em lei | X20: Nao aprovado em lei | Y20: http://www.teresina.pi.gov.br/sistemas/portalpmt/admin/upload/documentos/f77f8cb7ca.pdf www.semplam.teresina.pi.gov.br/plano-diretor-de-transporte-e-mobilidade-urbana-de-teresin https://drive.google.com/file/d/1qNII-txnol3hdKZfA75c1Cs1G2fZydMe/view | Z20: \\Londrina\sntmu$\a. DEPARTAMENTOS\i. DEPLAN\2.CGARG\SIMU\Levantamento Planos de Mobilidade 2019\Planos Municipais - exemplos\NORDESTE\Teresina_PI | AB20: Nao | AD20: Ofício Nº 102/2024 - GABS-STRANS | AE20: 45309 | AF20: strans.gabinete@gmail.com | AG20: Sim | AH20: Sim | AI20: Sim
A21: 2507507 | B21: NE | C21: PB | D21: João Pessoa | E21: RM de João Pessoa (PB) | F21: Sim | G21: Sim | H21: A | I21: A | J21: CD 1A | K21: 723515 | L21: De 500 mil a 1 milhão | M21: 833932 | N21: De 500 mil a 1 milhão | O21: 897633 | P21: De 500 mil a 1 milhão | Q21: Sim | R21: Sim | S21: Sim | T21: 2022 | U21: Sim | V21: Lei Municipal | W21: 14515/2022 | X21: 44706 | Y21: https://www.youtube.com/watch?v=FrB6X2hZTDg&feature=youtu.be www.planmob.joaopessoa.pb.gov.br | AB21: Nao | AD21: E-mail | AE21: 45649 | AF21: gabscaprobertorodrigues@gmail.com | AG21: Sim | AH21: Sim | AI21: Sim
A22: 3301702 | B22: SE | C22: RJ | D22: Duque de Caxias | E22: RM do Rio de Janeiro (RJ) | F22: Sim | G22: Sim | H22: B | I22: B | J22: CD 1A | K22: 855048 | L22: De 500 mil a 1 milhão | M22: 808161 | N22: De 500 mil a 1 milhão | O22: 866225 | P22: De 500 mil a 1 milhão | Q22: Sim | R22: Nao | S22: Nao respondeu | U22: Nao respondeu | V22: Nao respondeu | X22: Nao respondeu | AB22: Nao respondeu | AG22: Sim | AH22: Sim | AI22: Sim
A23: 3303500 | B23: SE | C23: RJ | D23: Nova Iguaçu | E23: RM do Rio de Janeiro (RJ) | F23: Sim | G23: Sim | H23: C | I23: C | J23: CD 1A | K23: 796257 | L23: De 500 mil a 1 milhão | M23: 785867 | N23: De 500 mil a 1 milhão | O23: 843220 | P23: De 500 mil a 1 milhão | Q23: Sim | R23: Nao | S23: Nao respondeu | U23: Nao respondeu | V23: Nao respondeu | X23: Nao respondeu | AB23: Nao respondeu | AG23: Sim | AH23: Sim | AI23: Sim
A24: 3548708 | B24: SE | C24: SP | D24: São Bernardo do Campo | E24: RM de São Paulo (SP) | F24: Sim | G24: Sim | H24: B | I24: B | J24: CD 1A | K24: 765463 | L24: De 500 mil a 1 milhão | M24: 810729 | N24: De 500 mil a 1 milhão | O24: 841154 | P24: De 500 mil a 1 milhão | Q24: Sim | R24: Sim | S24: Sim | T24: 2022 | U24: Sim | V24: Lei Municipal | W24: 7113/2022 | X24: 44743 | Y24: https://we.tl/t-4E7JauxhaE | Z24: N:\a. DEPARTAMENTOS\i. DEPLAN\2.CGARG\SIMU\Levantamento Planos de Mobilidade\Planos Municipais - exemplos\SUDESTE\São Paulo\São Bernardo_do_campo_SP | AB24: Nao | AD24: Email | AE24: 44771 | AF24: secretariadetransportes@saobernardo.sp.gov.br | AG24: Sim | AH24: Sim | AI24: Sim
A25: 2408102 | B25: NE | C25: RN | D25: Natal | E25: RM de Natal (RN) | F25: Sim | G25: Sim | H25: #N/A | I25: A | J25: CD 1A | K25: 803739 | L25: De 500 mil a 1 milhão | M25: 751300 | N25: De 500 mil a 1 milhão | O25: 784249 | P25: De 500 mil a 1 milhão | Q25: Sim | R25: Sim | S25: Sim | T25: 2022 | U25: Sim | V25: Decreto Municipal | W25: 12540/2022 | X25: 44727 | Z25: N:\a. DEPARTAMENTOS\i. DEPLAN\2.CGARG\SIMU\Levantamento Planos de Mobilidade\Planos Municipais - exemplos\NORDESTE\Natal_RN | AB25: Nao | AD25: Leandro Martins | AE25: 44727 | AF25: Leandro Martins | AG25: Sim | AH25: Sim | AI25: Sim
A26: 3547809 | B26: SE | C26: SP | D26: Santo André | E26: RM de São Paulo (SP) | F26: Sim | G26: Sim | H26: B | I26: B | J26: CD 1A | K26: 676407 | L26: De 500 mil a 1 milhão | M26: 748919 | N26: De 500 mil a 1 milhão | O26: 782048 | P26: De 500 mil a 1 milhão | Q26: Sim | R26: Sim | S26: Sim | T26: 2023 | U26: Sim | V26: Lei Municipal | W26: 10736/2023 | X26: 45268 | Z26: N:\a. DEPARTAMENTOS\i. DEPLAN\2.CGARG\SIMU\Levantamento Planos de Mobilidade\Planos Municipais - exemplos\SUDESTE\São Paulo\Santo André_SP | AB26: Nao | AD26: Email; Ofício 210.12.2023 UGP | AE26: 45279 | AF26: Ugp@santoandre.sp.gov.br | AG26: Sim | AH26: Sim | AI26: Sim
A27: 3552205 | B27: SE | C27: SP | D27: Sorocaba | E27: RM de Sorocaba (SP) | F27: Não | G27: Nao | H27: B | I27: B | J27: CD 1A | K27: 586625 | L27: De 500 mil a 1 milhão | M27: 723682 | N27: De 500 mil a 1 milhão | O27: 762172 | P27: De 500 mil a 1 milhão | Q27: Sim | R27: Sim | S27: Sim | T27: 2016 | U27: Sim | V27: Lei Municipal | W27: 11319/2016 | X27: 42494 | Z27: \\londrina\SNTMU$\a. DEPARTAMENTOS\i. DEPLAN\2.CGARG\SIMU\Levantamento Planos de Mobilidade 2019\Planos Municipais - exemplos\SUDESTE\São Paulo\Sorocaba_SP | AB27: Nao | AD27: Pemob 2024 | AE27: 45530 | AF27: Pemob 2024 | AG27: Sim | AH27: Sim | AI27: Sim
A28: 3170206 | B28: SE | C28: MG | D28: Uberlândia | E28: #N/A | F28: Não | G28: Nao | H28: A | I28: A | J28: CD 2C | K28: 604013 | L28: De 500 mil a 1 milhão | M28: 713224 | N28: De 500 mil a 1 milhão | O28: 761835 | P28: De 500 mil a 1 milhão | Q28: Sim | R28: Sim | S28: Sim | T28: 2025 | U28: Sim | V28: Decreto Municipal | W28: 21768/2025 | X28: 45751 | Y28: http://www.uberlandia.mg.gov.br/uploads/cms_b_arquivos/17532.pdf http://www.uberlandia.mg.gov.br/uploads/cms_b_arquivos/17533.pdf | Z28: L:\a. DEPARTAMENTOS\i. DEPLAN\2.CGARG\SIMU\Levantamento Planos de Mobilidade 2019\Planos Municipais - exemplos\SUDESTE\Minas Gerais\Uberlândia_MG | AB28: Nao | AD28: E-mail | AE28: 45755 | AF28: gabrielamendes@uberlandia.mg.gov.br | AG28: Sim | AH28: Sim | AI28: Sim
A29: 3534401 | B29: SE | C29: SP | D29: Osasco | E29: RM de São Paulo (SP) | F29: Sim | G29: Sim | H29: B | I29: #N/A | J29: CD 1A | K29: 666740 | L29: De 500 mil a 1 milhão | M29: 728615 | N29: De 500 mil a 1 milhão | O29: 759524 | P29: De 500 mil a 1 milhão | Q29: Sim | R29: Sim | S29: Sim | T29: 2016 | U29: Sim | V29: Lei Municipal | W29: 4.765/2016 | X29: 42558 | Y29: http://www.seplag.osasco.sp.gov.br/Content/uploads/publicacao/arquivo/d36ab199-8d5d-4f05-8886-ad0caaab5910.pdf | Z29: \\londrina\SNTMU$\a. DEPARTAMENTOS\i. DEPLAN\2.CGARG\SIMU\Levantamento Planos de Mobilidade 2019\Planos Municipais - exemplos\SUDESTE\São Paulo\Osasco_SP | AB29: Nao | AD29: Ofício nº 13/2019 | AE29: 43621 | AF29: FNP | AG29: Sim | AH29: Sim | AI29: Sim
A30: 3543402 | B30: SE | C30: SP | D30: Ribeirão Preto | E30: RM de Ribeirão Preto (SP) | F30: Não | G30: Nao | H30: A | I30: A | J30: CD 2A | K30: 604682 | L30: De 500 mil a 1 milhão | M30: 698642 | N30: De 500 mil a 1 milhão | O30: 731639 | P30: De 500 mil a 1 milhão | Q30: Sim | R30: Sim | S30: Sim | T30: 2012 | U30: Nao | V30: Nao aprovado em lei | X30: Nao aprovado em lei | Y30: http://www.ribeiraopreto.sp.gov.br/transerp/mobilidade/i07mobilidade.php | Z30: \\londrina\SNTMU$\a. DEPARTAMENTOS\i. DEPLAN\2.CGARG\SIMU\Levantamento Planos de Mobilidade 2019\Planos Municipais - exemplos\SUDESTE\São Paulo\Ribeirão Preto_SP | AB30: Sim | AC30: 44652 | AD30: Ofício nº 01/2016 | AE30: 42416 | AF30: FNP | AG30: Sim | AH30: Sim | AI30: Sim
A31: 3549904 | B31: SE | C31: SP | D31: São José dos Campos | E31: RM do Vale do Paraíba e Litoral Norte (SP) | F31: Não | G31: Nao | H31: B | I31: B | J31: CD 1A | K31: 629921 | L31: De 500 mil a 1 milhão | M31: 697054 | N31: De 500 mil a 1 milhão | O31: 727078 | P31: De 500 mil a 1 milhão | Q31: Sim | R31: Sim | S31: Sim | T31: 2016 | U31: Sim | V31: Lei Complementar | W31: 576/2016 | X31: 42444 | Y31: http://www.sjc.sp.gov.br/servicos/mobilidade-urbana/lei-de-mobilidade-urbana/ | Z31: \\londrina\SNTMU$\a. DEPARTAMENTOS\i. DEPLAN\2.CGARG\SIMU\Levantamento Planos de Mobilidade 2019\Planos Municipais - exemplos\SUDESTE\São Paulo\São José dos Campos_SP | AB31: Nao | AD31: Ofício nº 01/2016 | AE31: 42475 | AF31: jobquim@sãojosédoscampos.sp.gov.br/servicos | AG31: Sim | AH31: Sim | AI31: Sim
A32: 5103403 | B32: CO | C32: MT | D32: Cuiabá | E32: RM do Vale do Rio Cuiabá (MT) | F32: Não | G32: Nao | H32: A | I32: A | J32: CD 1A | K32: 551098 | L32: De 500 mil a 1 milhão | M32: 650877 | N32: De 500 mil a 1 milhão | O32: 691875 | P32: De 500 mil a 1 milhão | Q32: Sim | R32: Sim | S32: Sim | T32: 2024 | U32: Sim | V32: Decreto Municipal | W32: 10776/2024 | X32: 45645 | Y32: https://leismunicipais.com.br/a/mt/c/cuiaba/decreto/2024/1078/10776/decreto-n-10776-2024-institui-o-plano-de-mobilidade-urbana-do-municipio-de-cuiaba-planmob-cuiaba-e-estabelece-diretrizes-para-o-acompanhamento-e-o-monitoramento-de-sua-implementacao-avaliacao-e-revisao-periodica?q=contas+anuais | Z32: N:\a. DEPARTAMENTOS\i. DEPLAN\2.CGARG\SIMU\Levantamento Planos de Mobilidade\Planos Municipais - exemplos\CENTRO-OESTE\Cuiabá_MT | AB32: Nao | AD32: Internet | AE32: 45954 | AF32: Casa Civil - Seleção Novo PAC | AG32: Sim | AH32: Sim | AI32: Sim
A33: 2607901 | B33: NE | C33: PE | D33: Jaboatão dos Guararapes | E33: RM de Recife (PE) | F33: Sim | G33: Sim | H33: B | I33: B | J33: CD 1A | K33: 644620 | L33: De 500 mil a 1 milhão | M33: 644037 | N33: De 500 mil a 1 milhão | O33: 684293 | P33: De 500 mil a 1 milhão | Q33: Sim | R33: Sim | S33: Sim | T33: 2022 | U33: Sim | V33: Lei Municipal | W33: 1538/2022 | X33: 44881 | Y33: - | Z33: N:\a. DEPARTAMENTOS\i. DEPLAN\2.CGARG\SIMU\Levantamento Planos de Mobilidade\Planos Municipais - exemplos\NORDESTE\JaboatãodosGuararapes_PE | AB33: Nao | AD33: Email | AE33: 44883 | AF33: julilinsfialho@gmail.com | AG33: Sim | AH33: Sim | AI33: Sim
A34: 4209102 | B34: S | C34: SC | D34: Joinville | E34: RM do Norte/Nordeste Catarinense (SC); RM de Joinville (SC) | F34: Não | G34: Nao | H34: A | I34: A | J34: CD 2A | K34: 515288 | L34: De 500 mil a 1 milhão | M34: 616317 | N34: De 500 mil a 1 milhão | O34: 664541 | P34: De 500 mil a 1 milhão | Q34: Sim | R34: Sim | S34: Sim | T34: 2015 | U34: Sim | V34: Decreto Municipal | W34: 24.181/2015 | X34: 42090 | Y34: https://www.joinville.sc.gov.br/publicacoes/plano-de-mobilidade-de-joinville-planmob/ | Z34: L:\a. DEPARTAMENTOS\i. DEPLAN\2.CGARG\SIMU\Levantamento Planos de Mobilidade 2019\Planos Municipais - exemplos\SUL\Santa Catarina\Joinville_SC | AB34: Nao | AD34: Ofício nº 13/2019 | AE34: 43612 | AF34: FNP | AG34: Sim | AH34: Sim | AI34: Sim
A35: 2910800 | B35: NE | C35: BA | D35: Feira de Santana | E35: RM de Feira de Santana (BA) | F35: Não | G35: Nao | H35: B | I35: #N/A | J35: CD 2C | K35: 556642 | L35: De 500 mil a 1 milhão | M35: 616272 | N35: De 500 mil a 1 milhão | O35: 660806 | P35: De 500 mil a 1 milhão | Q35: Sim | R35: Sim | S35: Sim | T35: 2018 | U35: Sim | V35: Lei Complementar | W35: 112/2018 | X35: 43195 | AB35: Nao | AD35: Pemob/2019 | AE35: 43809 | AF35: Pesquisa PlanMob 2019 | AG35: Sim | AH35: Sim | AI35: Sim
A36: 3118601 | B36: SE | C36: MG | D36: Contagem | E36: RM de Belo Horizonte (MG) | F36: Sim | G36: Sim | H36: #N/A | I36: B | J36: CD 1A | K36: 603442 | L36: De 500 mil a 1 milhão | M36: 621863 | N36: De 500 mil a 1 milhão | O36: 651718 | P36: De 500 mil a 1 milhão | Q36: Sim | R36: Sim | S36: Sim | T36: 2016 | U36: Sim | V36: Lei Municipal | W36: 4830/2016 | X36: 42520 | Y36: http://www.contagem.mg.gov.br/arquivos/legislacao/lei_0048302016.pdf | Z36: L:\a. DEPARTAMENTOS\i. DEPLAN\2.CGARG\SIMU\Levantamento Planos de Mobilidade 2019\Planos Municipais - exemplos\SUDESTE\Minas Gerais\Contagem_MG | AB36: Nao | AD36: Ofício nº 01/2016 | AE36: 42396 | AF36: CBTU | AG36: Sim | AH36: Sim | AI36: Sim
A37: 2800308 | B37: NE | C37: SE | D37: Aracaju | E37: RM de Aracaju (SE) | F37: Não | G37: Nao | H37: A | I37: A | J37: CD 1A | K37: 571149 | L37: De 500 mil a 1 milhão | M37: 602757 | N37: De 500 mil a 1 milhão | O37: 630932 | P37: De 500 mil a 1 milhão | Q37: Sim | R37: Sim | S37: Sim | T37: 2010 | U37: Nao | V37: Nao aprovado em lei | X37: Nao aprovado em lei | Y37: http://aracaju.se.gov.br/index.php?act=leitura&codigo=68200 | Z37: L:\a. DEPARTAMENTOS\i. DEPLAN\2.CGARG\SIMU\Levantamento Planos de Mobilidade 2019\Planos Municipais - exemplos\NORDESTE\Aracaju_SE | AB37: Em revisao | AC37: 42705 | AD37: Ofício nº 01/2016 | AE37: 42426 | AF37: nº 01/2016.gabinear@gmail.br | AG37: Sim | AH37: Sim | AI37: Sim
A38: 4205407 | B38: S | C38: SC | D38: Florianópolis | E38: RM de Florianópolis (SC) | F38: Sim | G38: Sim | H38: A | I38: A | J38: CD 1A | K38: 421240 | L38: De 250 mil a 500 mil | M38: 537211 | N38: De 500 mil a 1 milhão | O38: 587486 | P38: De 500 mil a 1 milhão | Q38: Sim | R38: Sim | S38: Sim | T38: 2015 | U38: Sim | V38: Decreto Municipal | W38: 27311/2024 | X38: 45646 | Z38: L:\a. DEPARTAMENTOS\i. DEPLAN\2.CGARG\SIMU\Levantamento Planos de Mobilidade 2019\Planos Municipais - exemplos\SUL\Santa Catarina\Florianópolis_SC | AB38: Nao | AD38: E-mail | AE38: 45650 | AF38: pescador.americo@gmail.com | AG38: Sim | AH38: Sim | AI38: Sim
A39: 4113700 | B39: S | C39: PR | D39: Londrina | E39: RM de Londrina (PR) | F39: Não | G39: Nao | H39: A | I39: A | J39: CD 2A | K39: 506701 | L39: De 500 mil a 1 milhão | M39: 555965 | N39: De 500 mil a 1 milhão | O39: 581382 | P39: De 500 mil a 1 milhão | Q39: Sim | R39: Sim | S39: Sim | T39: 2022 | U39: Sim | V39: Decreto Municipal | W39: 865/2022 | X39: 44409 | Y39: http://ippul.londrina.pr.gov.br/index.php/plano-de-mobilidade.html | Z39: file:///L:/a.%20DEPARTAMENTOS/i.%20DEPLAN/2.CGARG/SIMU/Levantamento%20Planos%20de%20Mobilidade/Planos%20Municipais%20-%20exemplos/SUL/Paraná/Londrina_PR/2_audiencia_publica_planmob.pdf | AB39: Nao | AD39: Pemob 2024 | AE39: 45502 | AF39: ippul.transito@londrina.pr.gov.br | AG39: Sim | AH39: Sim | AI39: Sim
A40: 3205002 | B40: SE | C40: ES | D40: Serra | E40: RM da Grande Vitória (ES) | F40: Sim | G40: Sim | H40: B | I40: B | J40: CD 1A | K40: 409267 | L40: De 250 mil a 500 mil | M40: 520653 | N40: De 500 mil a 1 milhão | O40: 579720 | P40: De 500 mil a 1 milhão | Q40: Sim | R40: Sim | S40: Sim | T40: 2024 | U40: Sim | V40: Lei Complementar | W40: 5590/2024 | X40: 45426 | Y40: https://prefeiturasempapel.serra.es.gov.br/Arquivo/Documents/legislacao/html/L59902024.html?identificador=3100340038003300330039003A004C00 | AB40: Nao | AD40: Pemob 2024 | AE40: 45541 | AG40: Sim | AH40: Sim | AI40: Sim
A41: 3136702 | B41: SE | C41: MG | D41: Juiz de Fora | E41: #N/A | F41: Não | G41: Nao | H41: B | I41: B | J41: CD 2A | K41: 516247 | L41: De 500 mil a 1 milhão | M41: 540756 | N41: De 500 mil a 1 milhão | O41: 567730 | P41: De 500 mil a 1 milhão | Q41: Sim | R41: Sim | S41: Sim | T41: 2016 | U41: Sim | V41: Decreto Municipal | W41: 12829/2016 | X41: 42718 | Y41: https://www.pjf.mg.gov.br/secretarias/settra/servicos/arquivos/plano_mobilidade_151216.pdf | Z41: L:\a. DEPARTAMENTOS\i. DEPLAN\2.CGARG\SIMU\Levantamento Planos de Mobilidade 2019\Planos Municipais - exemplos\SUDESTE\Minas Gerais\Juiz de Fora_MG | AB41: Nao | AD41: E-mail | AE41: 45645 | AF41: jguarinello@gmail.com brunarocha@pjf.mg.gov.br; vmauricio@pjf.mg.gov.br | AG41: Sim | AH41: Sim | AI41: Sim
A42: 5201405 | B42: CO | C42: GO | D42: Aparecida de Goiânia | E42: RM de Goiânia (GO) | F42: Sim | G42: Sim | H42: #N/A | I42: #N/A | J42: CD 1A | K42: 455657 | L42: De 250 mil a 500 mil | M42: 527796 | N42: De 500 mil a 1 milhão | O42: 556021 | P42: De 500 mil a 1 milhão | Q42: Sim | R42: Sim | S42: Nao | U42: Nao possui plano | V42: Nao possui plano | X42: Nao possui plano | AB42: Sim | AC42: 44866 | AD42: E-mail (Ofício 275/2024 GAB) | AE42: 45404 | AF42: gabinete.mobilidade@aparecida.go.gov.br | AG42: Sim | AH42: Sim | AI42: Sim
A43: 3301009 | B43: SE | C43: RJ | D43: Campos dos Goytacazes | E43: #N/A | F43: Não | G43: Nao | H43: B | I43: B | J43: CD 2A | K43: 463731 | L43: De 250 mil a 500 mil | M43: 483540 | N43: De 250 mil a 500 mil | O43: 519259 | P43: De 500 mil a 1 milhão | Q43: Sim | R43: Sim | S43: Sim | T43: 2022 | U43: Sim | V43: Lei Municipal | W43: 9137/2022 | X43: 44662 | Z43: N:\a. DEPARTAMENTOS\i. DEPLAN\2.CGARG\SIMU\Levantamento Planos de Mobilidade\Planos Municipais - exemplos\SUDESTE\Rio de Janeiro\Campos dos Goytacazes_RJ | AB43: Nao | AC43: - | AD43: Email | AE43: 44663 | AF43: smpuma@campos.rj.gov.br | AG43: Sim | AH43: Sim | AI43: Sim
A44: 3300456 | B44: SE | C44: RJ | D44: Belford Roxo | E44: RM do Rio de Janeiro (RJ) | F44: Sim | G44: Sim | H44: #N/A | I44: #N/A | J44: CD 1B | K44: 469332 | L44: De 250 mil a 500 mil | M44: 483087 | N44: De 250 mil a 500 mil | O44: 518384 | P44: De 500 mil a 1 milhão | Q44: Sim | R44: Sim | S44: Nao | U44: Nao possui plano | V44: Nao possui plano | X44: Nao possui plano | AB44: Sim | AC44: Sem previsao | AD44: Ofício nº 210/2015 | AE44: 42044 | AF44: chefi#n/ddeg#n/dbisetesmtt@gnº 210/2015.com | AG44: Sim | AH44: Sim | AI44: Sim
A45: 1100205 | B45: N | C45: RO | D45: Porto Velho | E45: RM de Porto Velho (RO) | F45: Não | G45: Nao | H45: A | I45: A | J45: CD 2A | K45: 428527 | L45: De 250 mil a 500 mil | M45: 460434 | N45: De 250 mil a 500 mil | O45: 517709 | P45: De 500 mil a 1 milhão | Q45: Sim | R45: Sim | S45: Sim | T45: 2022 | U45: Sim | V45: Lei complementar | W45: 914/2022 | X45: 44820 | Y45: - | Z45: N:\a. DEPARTAMENTOS\i. DEPLAN\2.CGARG\SIMU\Levantamento Planos de Mobilidade\Planos Municipais - exemplos\NORTE\Porto Velho_RO | AB45: Nao | AD45: Email | AE45: 44872 | AF45: adriana.souza@portovelho.ro.gov.br | AG45: Sim | AH45: Sim | AI45: Sim
A46: 3303302 | B46: SE | C46: RJ | D46: Niterói | E46: RM do Rio de Janeiro (RJ) | F46: Sim | G46: Sim | H46: B | I46: B | J46: CD 1A | K46: 487562 | L46: De 250 mil a 500 mil | M46: 481749 | N46: De 250 mil a 500 mil | O46: 516787 | P46: De 500 mil a 1 milhão | Q46: Sim | R46: Sim | S46: Sim | T46: 2018 | U46: Sim | V46: Decreto Municipal | W46: 15658/2024 | X46: 45646 | Y46: http://www.niteroi.rj.gov.br/pmus/ | AB46: Nao | AD46: E-mail | AE46: 45649 | AF46: rafael@egp.niteroi.rj.gov.br | AG46: Sim | AH46: Sim | AI46: Sim
A47: 1500800 | B47: N | C47: PA | D47: Ananindeua | E47: RM de Belém (PA) | F47: Sim | G47: Sim | H47: C | I47: C | J47: CD 1B | K47: 471980 | L47: De 250 mil a 500 mil | M47: 478778 | N47: De 250 mil a 500 mil | O47: 509227 | P47: De 500 mil a 1 milhão | Q47: Sim | R47: Sim | S47: Nao | U47: Nao possui plano | V47: Nao possui plano | X47: Nao possui plano | AB47: Sim | AC47: 42095 | AD47: Ofício nº 210/2015 | AE47: 42075 | AG47: Sim | AH47: Sim | AI47: Sim
A48: 3205200 | B48: SE | C48: ES | D48: Vila Velha | E48: RM da Grande Vitória (ES) | F48: Sim | G48: Sim | H48: B | I48: B | J48: CD 1A | K48: 414586 | L48: De 250 mil a 500 mil | M48: 467722 | N48: De 250 mil a 500 mil | O48: 506779 | P48: De 500 mil a 1 milhão | Q48: Sim | R48: Sim | S48: Sim | T48: 2022 | U48: Sim | V48: Lei Municipal | W48: 6756/2022 | X48: 44893 | Z48: N:\a. DEPARTAMENTOS\i. DEPLAN\2.CGARG\SIMU\Levantamento Planos de Mobilidade\Planos Municipais - exemplos\SUDESTE\Espírito Santo\Vila Velha_ES | AB48: Nao | AD48: 59016.001806/2022-11 (4042143) | AE48: 44896 | AF48: Renata Morandi Lóra | AG48: Sim | AH48: Sim | AI48: Sim
A49: 3549805 | B49: SE | C49: SP | D49: São José do Rio Preto | E49: RM de São José do Rio Preto (SP) | F49: Não | G49: Nao | H49: B | I49: B | J49: CD 2A | K49: 408258 | L49: De 250 mil a 500 mil | M49: 480393 | N49: De 250 mil a 500 mil | O49: 504166 | P49: De 500 mil a 1 milhão | Q49: Sim | R49: Sim | S49: Sim | T49: 2015 | U49: Sim | V49: Lei Municipal | W49: 11.736/2015 | X49: 42111 | Y49: http://www.riopreto.sp.gov.br/PortalGOV/do/subportais_Preview?c=137263 | Z49: \\londrina\SNTMU$\a. DEPARTAMENTOS\i. DEPLAN\2.CGARG\SIMU\Levantamento Planos de Mobilidade 2019\Planos Municipais - exemplos\SUDESTE\São Paulo\São José do Rio Preto_SP | AB49: Nao | AD49: Ofício nº 01/2016 | AE49: 42394 | AF49: jobquim@sãojosédoriopreto.sp.gov.br | AG49: Sim | AH49: Sim | AI49: Sim
A50: 1600303 | B50: N | C50: AP | D50: Macapá | E50: RM de Macapá (AP) | F50: Não | G50: Nao | H50: A | I50: #N/A | J50: CD 2A | K50: 398204 | L50: De 250 mil a 500 mil | M50: 442933 | N50: De 250 mil a 500 mil | O50: 489676 | P50: De 250 mil a 500 mil | Q50: Sim | R50: Sim | S50: Sim | T50: 2024 | U50: Sim | V50: Decreto Municipal | W50: 2631/2024 | X50: 45645 | Z50: L:\a. DEPARTAMENTOS\i. DEPLAN\2.CGARG\SIMU\Levantamento Planos de Mobilidade 2019\Planos Municipais - exemplos\NORTE\Macapá_AP | AB50: Nao | AD50: E-mail | AE50: 45646 | AF50: notificacao@1doc.com.br; Ofício nº 491/2024/GAB/PRES/CTMac | AG50: Sim | AH50: Sim | AI50: Sim
A51: 1400100 | B51: N | C51: RR | D51: Boa Vista | E51: RM da Capital (Boa Vista/RR) | F51: Não | G51: Nao | H51: A | I51: #N/A | J51: CD 2C | K51: 284313 | L51: De 250 mil a 500 mil | M51: 413486 | N51: De 250 mil a 500 mil | O51: 485477 | P51: De 250 mil a 500 mil | Q51: Sim | R51: Sim | S51: Sim | T51: 2025 | U51: Sim | V51: Lei Municipal | W51: 2704/2025 | X51: 45824 | Y51: https://sapl.boavista.rr.leg.br/media/sapl/public/normajuridica/2025/4909/lei_no_2.704_16.06.2024_-_dom_no_6374_-_executivo.pdf | Z51: N:\a. DEPARTAMENTOS\i. DEPLAN\2.CGARG\SIMU\Levantamento Planos de Mobilidade\Planos Municipais - exemplos\NORTE\Boa Vista_RR | AB51: Nao | AD51: Pemob 2025 | AE51: 45891 | AF51: Nadia Leandra Pereira | AG51: Sim | AH51: Sim | AI51: Sim
A52: 4305108 | B52: S | C52: RS | D52: Caxias do Sul | E52: RM da Serra Gaúcha (RS) | F52: Não | G52: Nao | H52: B | I52: B | J52: CD 2A | K52: 435564 | L52: De 250 mil a 500 mil | M52: 463501 | N52: De 250 mil a 500 mil | O52: 479599 | P52: De 250 mil a 500 mil | Q52: Sim | R52: Sim | S52: Sim | T52: 2023 | U52: Sim | V52: Lei Municipal | W52: 9076/2023 | X52: 45281 | Z52: N:\a. DEPARTAMENTOS\i. DEPLAN\2.CGARG\SIMU\Levantamento Planos de Mobilidade\Planos Municipais - exemplos\SUL\Rio Grande do Sul\Caxias do Sul_RS | AB52: Nao | AD52: Protocolo SEI 4978991 | AE52: 45383 | AF52: Adiló Angelo Didomenico | AG52: Sim | AH52: Sim | AI52: Sim
A53: 3530607 | B53: SE | C53: SP | D53: Mogi das Cruzes | E53: RM de São Paulo (SP) | F53: Sim | G53: Sim | H53: B | I53: B | J53: CD 1A | K53: 387779 | L53: De 250 mil a 500 mil | M53: 451505 | N53: De 250 mil a 500 mil | O53: 470302 | P53: De 250 mil a 500 mil | Q53: Sim | R53: Sim | S53: Sim | T53: 2016 | U53: Nao | V53: Nao aprovado em lei | X53: Nao aprovado em lei | Y53: http://www.mogidascruzes.sp.gov.br/pagina/secretaria-de-transportes/plano-de-mobilidade-urbana | Z53: \\londrina\SNTMU$\a. DEPARTAMENTOS\i. DEPLAN\2.CGARG\SIMU\Levantamento Planos de Mobilidade 2019\Planos Municipais - exemplos\SUDESTE\São Paulo\Mogi das Cruzes_SP | AB53: Nao | AD53: Ofício nº 01/2016 | AE53: 42424 | AF53: jobquim@mogidascruzes.sp.gov.br | AG53: Sim | AH53: Sim | AI53: Sim
A54: 3305109 | B54: SE | C54: RJ | D54: São João de Meriti | E54: RM do Rio de Janeiro (RJ) | F54: Sim | G54: Sim | H54: B | I54: B | J54: CD 1B | K54: 458673 | L54: De 250 mil a 500 mil | M54: 440962 | N54: De 250 mil a 500 mil | O54: 466503 | P54: De 250 mil a 500 mil | Q54: Sim | R54: Sim | S54: Nao | U54: Nao possui plano | V54: Nao possui plano | X54: Nao possui plano | AB54: Sim | AC54: 44896 | AD54: Ofício nº 10/2016 | AE54: 42495 | AF54: FNP | AG54: Sim | AH54: Sim | AI54: Sim
A55: 3525904 | B55: SE | C55: SP | D55: Jundiaí | E55: RM de Jundiaí (SP) | F55: Não | G55: Nao | H55: B | I55: B | J55: CD 2A | K55: 370126 | L55: De 250 mil a 500 mil | M55: 443221 | N55: De 250 mil a 500 mil | O55: 463039 | P55: De 250 mil a 500 mil | Q55: Sim | R55: Sim | S55: Sim | T55: 2022 | U55: Sim | V55: Lei Municipal | W55: 9752/2022 | X55: 44681 | Y55: https://jundiai.sp.gov.br/transportes/plano-de-mobilidade-urbana-de-jundiai/ https://imprensaoficial.jundiai.sp.gov.br/wp-content/uploads/2022/04/131ff44a-8ac4-4561-80c8-335296b29a98_Edicao-5081-30-04-2022.pdf | Z55: N:\a. DEPARTAMENTOS\i. DEPLAN\2.CGARG\SIMU\Levantamento Planos de Mobilidade\Planos Municipais - exemplos\SUDESTE\São Paulo\Jundiaí_SP | AB55: Nao | AD55: Contato Telefônico | AE55: 44706 | AF55: ljpinheiro@jundiai.sp.gov.br | AG55: Sim | AH55: Sim | AI55: Sim
A56: 2504009 | B56: NE | C56: PB | D56: Campina Grande | E56: RM de Campina Grande (PB) | F56: Não | G56: Nao | H56: B | I56: B | J56: CD 2A | K56: 385213 | L56: De 250 mil a 500 mil | M56: 419379 | N56: De 250 mil a 500 mil | O56: 443911 | P56: De 250 mil a 500 mil | Q56: Sim | R56: Sim | S56: Sim | T56: 2015 | U56: Sim | V56: Lei Municipal | W56: 095/2015 | X56: 42110 | AB56: Nao | AD56: PEMOB 2024 | AE56: 45523 | AF56: PEMOB 2024 | AG56: Sim | AH56: Sim | AI56: Sim
A57: 3538709 | B57: SE | C57: SP | D57: Piracicaba | E57: RM de Piracicaba (SP) | F57: Não | G57: Nao | H57: B | I57: B | J57: CD 2A | K57: 364571 | L57: De 250 mil a 500 mil | M57: 423323 | N57: De 250 mil a 500 mil | O57: 440835 | P57: De 250 mil a 500 mil | Q57: Sim | R57: Sim | S57: Sim | T57: 2023 | U57: Sim | V57: Lei Complementar | W57: 452/2023 | X57: 45280 | Y57: https://www.legislacaodigital.com.br/Piracicaba-SP/LeisComplementares/452 | Z57: \\londrina\SNTMU$\a. DEPARTAMENTOS\i. DEPLAN\2.CGARG\SIMU\Levantamento Planos de Mobilidade 2019\Planos Municipais - exemplos\SUDESTE\São Paulo\Piracicaba_SP | AA57: https://app.powerbi.com/view?r=eyJrIjoiMDg3MWQ3NjUtNDQxNy00Nzk1LWI5N2EtZmEyYzI1NmNmMDAzIiwidCI6IjFiNTg1YzllLTRmMTctNDhiMS04N2I0LTQ2MTIwYjk4N2MzYiJ9; https://app.powerbi.com/view?r=eyJrIjoiNjJiNWNmZmMtYWZlNi00Y2ExLTkzZDYtOTM1ZWE1OGNjNWU3IiwidCI6IjFiNTg1YzllLTRmMTctNDhiMS04N2I0LTQ2MTIwYjk4N2MzYiJ9; https://app.powerbi.com/view?r=eyJrIjoiMDJiNDQxNzYtMzYwYS00NWVmLWFmNzQtYjk5NTI0MWI4MDIyIiwidCI6IjFiNTg1YzllLTRmMTctNDhiMS04N2I0LTQ2MTIwYjk4N2MzYiJ9 | AB57: Nao | AD57: Pemob 2025 | AE57: 45891 | AF57: Eliezer de Castro | AG57: Sim | AH57: Sim | AI57: Sim
A58: 3143302 | B58: SE | C58: MG | D58: Montes Claros | E58: #N/A | F58: Não | G58: Nao | H58: B | I58: B | J58: CD 2C | K58: 361915 | L58: De 250 mil a 500 mil | M58: 414240 | N58: De 250 mil a 500 mil | O58: 437601 | P58: De 250 mil a 500 mil | Q58: Sim | R58: Sim | S58: Nao | U58: Nao possui plano | V58: Nao possui plano | X58: Nao possui plano | AB58: Nao | AD58: Ofício nº 907/2014 | AE58: 41992 | AG58: Sim | AH58: Sim | AI58: Sim
A59: 3106705 | B59: SE | C59: MG | D59: Betim | E59: RM de Belo Horizonte (MG) | F59: Sim | G59: Sim | H59: #N/A | I59: #N/A | J59: CD 1A | K59: 378089 | L59: De 250 mil a 500 mil | M59: 411846 | N59: De 250 mil a 500 mil | O59: 431433 | P59: De 250 mil a 500 mil | Q59: Sim | R59: Sim | S59: Sim | T59: 2016 | U59: Nao | V59: Nao aprovado em lei | X59: Nao aprovado em lei | Z59: N:\a. DEPARTAMENTOS\i. DEPLAN\2.CGARG\SIMU\Levantamento Planos de Mobilidade\Planos Municipais - exemplos\SUDESTE\Minas Gerais\Betim_MG | AB59: Nao | AD59: Email | AE59: 44797 | AF59: presidencia.ecos@gmail.com | AG59: Sim | AH59: Sim | AI59: Sim
A60: 4115200 | B60: S | C60: PR | D60: Maringá | E60: RM de Maringá (PR) | F60: Não | G60: Nao | H60: B | I60: B | J60: CD 2A | K60: 357077 | L60: De 250 mil a 500 mil | M60: 409657 | N60: De 250 mil a 500 mil | O60: 429660 | P60: De 250 mil a 500 mil | Q60: Sim | R60: Sim | S60: Sim | T60: 2022 | U60: Sim | V60: Lei Municipal | W60: 11518/2022 | X60: 44840 | Z60: L:\a. DEPARTAMENTOS\i. DEPLAN\2.CGARG\SIMU\Levantamento Planos de Mobilidade 2019\Planos Municipais - exemplos\SUL\Paraná\Maringá_PR | AB60: Nao | AD60: Email | AE60: 44718 | AF60: semob_mobilidade@maringa.pr.gov.br | AG60: Sim | AH60: Sim | AI60: Sim
A61: 3548500 | B61: SE | C61: SP | D61: Santos | E61: RM da Baixada Santista (SP) | F61: Sim | G61: Sim | H61: A | I61: A | J61: CD 1A | K61: 419400 | L61: De 250 mil a 500 mil | M61: 418608 | N61: De 250 mil a 500 mil | O61: 429547 | P61: De 250 mil a 500 mil | Q61: Sim | R61: Sim | S61: Sim | T61: 2019 | U61: Sim | V61: Lei Complementar | W61: 1.087/2019 | X61: 43830 | Y61: https://diariooficial.santos.sp.gov.br/edicoes/inicio/download/2019-12-31 | Z61: \\londrina\SNTMU$\a. DEPARTAMENTOS\i. DEPLAN\2.CGARG\SIMU\Levantamento Planos de Mobilidade 2019\Planos Municipais - exemplos\SUDESTE\São Paulo\Santos_SP | AB61: Nao | AD61: Pemob/2020 | AE61: 44136 | AF61: Pemob 2020 | AG61: Sim | AH61: Sim | AI61: Sim
A62: 3529401 | B62: SE | C62: SP | D62: Mauá | E62: RM de São Paulo (SP) | F62: Sim | G62: Sim | H62: C | I62: C | J62: CD 1B | K62: 417064 | L62: De 250 mil a 500 mil | M62: 418261 | N62: De 250 mil a 500 mil | O62: 429014 | P62: De 250 mil a 500 mil | Q62: Sim | R62: Sim | S62: Sim | T62: 2017 | U62: Sim | V62: Lei Municipal | W62: 5.250/2017 | X62: 42978 | AB62: Nao | AD62: PEMOB 2021 | AE62: 44393 | AF62: PEMOB 2021 | AG62: Sim | AH62: Sim | AI62: Sim
A63: 5201108 | B63: CO | C63: GO | D63: Anápolis | E63: #N/A | F63: Não | G63: Nao | H63: B | I63: B | J63: CD 2C | K63: 334613 | L63: De 250 mil a 500 mil | M63: 398869 | N63: De 250 mil a 500 mil | O63: 420300 | P63: De 250 mil a 500 mil | Q63: Sim | R63: Sim | S63: Sim | T63: 2022 | U63: Sim | V63: Decreto Municipal | W63: 48128/2022 | X63: 44796 | Z63: N:\a. DEPARTAMENTOS\i. DEPLAN\2.CGARG\SIMU\Levantamento Planos de Mobilidade\Planos Municipais - exemplos\CENTRO-OESTE\Anápolis_GO | AB63: Sim | AC63: 42095 | AD63: Anexo à proposta 37748/2024 de emenda parlamentar | AE63: 45656 | AF63: Anexo à proposta 37748/2024 de emenda parlamentar | AG63: Sim | AH63: Sim | AI63: Sim
A64: 2611101 | B64: NE | C64: PE | D64: Petrolina | E64: RIDE do Polo Petrolina/PE e Juazeiro/BA | F64: Não | G64: Nao | H64: B | I64: B | J64: CD 2A | K64: 293962 | L64: De 250 mil a 500 mil | M64: 386791 | N64: De 250 mil a 500 mil | O64: 418444 | P64: De 250 mil a 500 mil | Q64: Sim | R64: Sim | S64: Sim | T64: 2016 | U64: Sim | V64: Lei Municipal | W64: 2.828/2016 | X64: 42493 | Y64: http://45.76.165.190:8080/cm_pet/sapl/sapl_documentos/norma_juridica/2712_texto_integral | Z64: L:\a. DEPARTAMENTOS\i. DEPLAN\2.CGARG\SIMU\Levantamento Planos de Mobilidade 2019\Planos Municipais - exemplos\NORDESTE\Petrolina_PE | AB64: Nao | AD64: Ofício nº 10/2016 | AE64: 42433 | AG64: Sim | AH64: Sim | AI64: Sim
A65: 2604106 | B65: NE | C65: PE | D65: Caruaru | E65: #N/A | F65: Não | G65: Nao | H65: B | I65: B | J65: CD 2C | K65: 314912 | L65: De 250 mil a 500 mil | M65: 377911 | N65: De 250 mil a 500 mil | O65: 405408 | P65: De 250 mil a 500 mil | Q65: Sim | R65: Sim | S65: Sim | T65: 2022 | U65: Sim | V65: Decreto Municipal | W65: 43/2022 | X65: 44663 | Z65: N:\a. DEPARTAMENTOS\i. DEPLAN\2.CGARG\SIMU\Levantamento Planos de Mobilidade\Planos Municipais - exemplos\NORDESTE\Caruaru_PE | AB65: Nao | AD65: Email | AE65: 44771 | AF65: notificacao@1doc.com.br | AG65: Sim | AH65: Sim | AI65: Sim
A66: 3513801 | B66: SE | C66: SP | D66: Diadema | E66: RM de São Paulo (SP) | F66: Sim | G66: Sim | H66: #N/A | I66: #N/A | J66: CD 1B | K66: 386089 | L66: De 250 mil a 500 mil | M66: 393237 | N66: De 250 mil a 500 mil | O66: 403579 | P66: De 250 mil a 500 mil | Q66: Sim | R66: Sim | S66: Sim | T66: 2021 | U66: Sim | V66: Lei Municipal | W66: 4.150/2021 | X66: 44516 | Z66: N:\a. DEPARTAMENTOS\i. DEPLAN\2.CGARG\SIMU\Levantamento Planos de Mobilidade\Planos Municipais - exemplos\SUDESTE\São Paulo\Diadema_SP | AB66: Nao | AD66: SEI | AE66: 44524 | AF66: 59000.023479/2021-38 | AG66: Sim | AH66: Sim | AI66: Sim
A67: 3510609 | B67: SE | C67: SP | D67: Carapicuíba | E67: RM de São Paulo (SP) | F67: Sim | G67: Sim | H67: C | I67: C | J67: CD 1B | K67: 369584 | L67: De 250 mil a 500 mil | M67: 386984 | N67: De 250 mil a 500 mil | O67: 398236 | P67: De 250 mil a 500 mil | Q67: Sim | R67: Sim | S67: Sim | T67: 2019 | U67: Sim | V67: Lei Municipal | W67: 3623/2019 | X67: 43783 | Z67: N:\a. DEPARTAMENTOS\i. DEPLAN\2.CGARG\SIMU\Levantamento Planos de Mobilidade\Planos Municipais - exemplos\SUDESTE\São Paulo\Carapicuiba_SP | AB67: Nao | AD67: Contato Telefônico; Email | AE67: 44706 | AF67: gabinete@carapicuiba.sp.gov.br | AG67: Sim | AH67: Sim | AI67: Sim
A68: 2933307 | B68: NE | C68: BA | D68: Vitória da Conquista | E68: #N/A | F68: Não | G68: Nao | H68: B | I68: B | J68: CD 2C | K68: 306866 | L68: De 250 mil a 500 mil | M68: 370879 | N68: De 250 mil a 500 mil | O68: 396613 | P68: De 250 mil a 500 mil | Q68: Sim | R68: Sim | S68: Nao | U68: Nao possui plano | V68: Nao possui plano | X68: Nao possui plano | AB68: Sim | AC68: Sem previsao | AD68: Ofício nº 01/2016 | AE68: 42395 | AF68: chefibNgbbinetesmtt@gnº 01/2016.com | AG68: Sim | AH68: Sim | AI68: Sim
A69: 3506003 | B69: SE | C69: SP | D69: Bauru | E69: #N/A | F69: Não | G69: Nao | H69: B | I69: #N/A | J69: CD 2A | K69: 343937 | L69: De 250 mil a 500 mil | M69: 379146 | N69: De 250 mil a 500 mil | O69: 392947 | P69: De 250 mil a 500 mil | Q69: Sim | R69: Sim | S69: Sim | T69: 2019 | U69: Sim | V69: Lei Municipal | W69: 14446/2019 | X69: 43791 | Y69: https://www.emdurb.com.br/mobilidade/leismob | Z69: N:\a. DEPARTAMENTOS\i. DEPLAN\2.CGARG\SIMU\Levantamento Planos de Mobilidade\Planos Municipais - exemplos\SUDESTE\São Paulo\Bauru_SP | AB69: Nao | AD69: Email | AE69: 44806 | AF69: fabianalima@bauru.sp.gov.br | AG69: Sim | AH69: Sim | AI69: Sim
A70: 1200401 | B70: N | C70: AC | D70: Rio Branco | E70: #N/A | F70: Não | G70: Nao | H70: A | I70: A | J70: CD 2C | K70: 336038 | L70: De 250 mil a 500 mil | M70: 364756 | N70: De 250 mil a 500 mil | O70: 389001 | P70: De 250 mil a 500 mil | Q70: Sim | R70: Sim | S70: Sim | T70: 2015 | U70: Sim | V70: Decreto Municipal | W70: 392/2015 | X70: 42114 | Y70: http://riobranco.ac.gov.br/index.php/plano-de-mobilidade-urbana-de-rio-branco.html | Z70: L:\a. DEPARTAMENTOS\i. DEPLAN\2.CGARG\SIMU\Levantamento Planos de Mobilidade 2019\Planos Municipais - exemplos\NORTE\Rio Branco_AC | AB70: Nao | AD70: Ofício nº 01/2016 | AE70: 42436 | AG70: Sim | AH70: Sim | AI70: Sim
A71: 4202404 | B71: S | C71: SC | D71: Blumenau | E71: RM do Vale Europeu (SC) | F71: Não | G71: Nao | H71: B | I71: B | J71: CD 2A | K71: 309011 | L71: De 250 mil a 500 mil | M71: 361261 | N71: De 250 mil a 500 mil | O71: 385558 | P71: De 250 mil a 500 mil | Q71: Sim | R71: Sim | S71: Sim | T71: 2018 | U71: Sim | V71: Decreto Municipal | W71: 11748/2018 | X71: 43197 | Y71: https://www.blumenau.sc.gov.br/governo/secretaria-de-desenvolvimento-urbano/pagina/plano-mobilidade-sedur https://leismunicipais.com.br/a/sc/b/blumenau/decreto/2018/1175/11748/decreto-n-11748-2018-aprova-o-plano-de-mobilidade-urbana-do-municipio-de-blumenau?q=mobilidade | Z71: L:\a. DEPARTAMENTOS\i. DEPLAN\2.CGARG\SIMU\Levantamento Planos de Mobilidade 2019\Planos Municipais - exemplos\SUL\Santa Catarina\Blumenau_SC | AB71: Nao | AD71: Ofício nº 21/2019 | AE71: 43713 | AF71: Pesquisa PlanMob 2019 | AG71: Sim | AH71: Sim | AI71: Sim
A72: 3523107 | B72: SE | C72: SP | D72: Itaquaquecetuba | E72: RM de São Paulo (SP) | F72: Sim | G72: Sim | H72: C | I72: #N/A | J72: CD 1B | K72: 321770 | L72: De 250 mil a 500 mil | M72: 369275 | N72: De 250 mil a 500 mil | O72: 382983 | P72: De 250 mil a 500 mil | Q72: Sim | R72: Sim | S72: Sim | T72: 2022 | U72: Sim | V72: Decreto Municipal | W72: 8189/2023 | X72: 44986 | Z72: N:\a. DEPARTAMENTOS\i. DEPLAN\2.CGARG\SIMU\Levantamento Planos de Mobilidade\Planos Municipais - exemplos\SUDESTE\São Paulo\Itaquaquecetuba_SP | AB72: Nao | AD72: Email | AE72: 44988 | AF72: itaquaengenharia@outlook.com | AG72: Sim | AH72: Sim | AI72: Sim
A73: 2303709 | B73: NE | C73: CE | D73: Caucaia | E73: RM de Fortaleza (CE) | F73: Sim | G73: Sim | H73: B | I73: B | J73: CD 1B | K73: 325441 | L73: De 250 mil a 500 mil | M73: 355679 | N73: De 250 mil a 500 mil | O73: 378406 | P73: De 250 mil a 500 mil | Q73: Sim | R73: Sim | S73: Sim | T73: 2021 | U73: Sim | V73: Lei Municipal | W73: 3396/2021 | X73: 44553 | Y73: http://www.caucaia.ce.gov.br/admin/view/docsoficiais/lei_ordinaria/html/lei_ord3396_20220118190025.html | Z73: N:\a. DEPARTAMENTOS\i. DEPLAN\2.CGARG\SIMU\Levantamento Planos de Mobilidade\Planos Municipais - exemplos\NORDESTE\Caucaia_CE | AB73: Nao | AD73: Leandro Martins | AE73: 44735 | AF73: Leandro Martins | AG73: Sim | AH73: Sim | AI73: Sim
A74: 3201308 | B74: SE | C74: ES | D74: Cariacica | E74: RM da Grande Vitória (ES) | F74: Sim | G74: Sim | H74: C | I74: C | J74: CD 1A | K74: 348738 | L74: De 250 mil a 500 mil | M74: 353491 | N74: De 250 mil a 500 mil | O74: 376200 | P74: De 250 mil a 500 mil | Q74: Sim | R74: Sim | S74: Sim | T74: 2023 | U74: Sim | V74: Lei Municipal | W74: 6481/2023 | X74: 45117 | Y74: https://cariacica.camarasempapel.com.br/Arquivo/Documents/legislacao/image/L64812023.pdf http://www3.camaracariacica.es.gov.br/Sistema/Protocolo/Processo2/Digital.aspx?id=108960&arquivo=Arquivo/Documents/PLE/PLE242019-23082019131553-assinado.pdf#P108960 | Z74: L:\a. DEPARTAMENTOS\i. DEPLAN\2.CGARG\SIMU\Levantamento Planos de Mobilidade\Planos Municipais - exemplos\SUDESTE\Espírito Santo\Cariacica_ES | AB74: Nao | AD74: Pemob/2024 | AE74: 45512 | AF74: captacao@cariacica.es.gov.br | AG74: Sim | AH74: Sim | AI74: Sim
A75: 4119905 | B75: S | C75: PR | D75: Ponta Grossa | E75: #N/A | F75: Não | G75: Nao | H75: B | I75: B | J75: CD 2A | K75: 311611 | L75: De 250 mil a 500 mil | M75: 358371 | N75: De 250 mil a 500 mil | O75: 375632 | P75: De 250 mil a 500 mil | Q75: Sim | R75: Sim | S75: Sim | T75: 2022 | U75: Sim | V75: Lei Municipal | W75: 14311/2022 | X75: 44769 | Z75: N:\a. DEPARTAMENTOS\i. DEPLAN\2.CGARG\SIMU\Levantamento Planos de Mobilidade\Planos Municipais - exemplos\SUL\Paraná\Ponta Grossa_PR | AB75: Nao | AD75: Email | AE75: 44776 | AF75: diegofelipevaz@gmail.com | AG75: Sim | AH75: Sim | AI75: Sim
A76: 3541000 | B76: SE | C76: SP | D76: Praia Grande | E76: RM da Baixada Santista (SP) | F76: Sim | G76: Sim | H76: A | I76: A | J76: CD 1A | K76: 262051 | L76: De 250 mil a 500 mil | M76: 349935 | N76: De 250 mil a 500 mil | O76: 368539 | P76: De 250 mil a 500 mil | Q76: Sim | R76: Sim | S76: Sim | T76: 2017 | U76: Sim | V76: Lei Complementar | W76: 760/2017 | X76: 43069 | Y76: http://www.praiagrande.sp.gov.br/Administracao/leisdecretos_view.asp?codLeis=5492&Acao=busca | Z76: \\londrina\SNTMU$\a. DEPARTAMENTOS\i. DEPLAN\2.CGARG\SIMU\Levantamento Planos de Mobilidade 2019\Planos Municipais - exemplos\SUDESTE\São Paulo\Praia Grande_SP | AB76: Nao | AD76: Ofício nº 13/2019 | AE76: 43615 | AF76: FNP | AG76: Sim | AH76: Sim | AI76: Sim
A77: 4104808 | B77: S | C77: PR | D77: Cascavel | E77: RM de Cascavel (PR) | F77: Não | G77: Nao | H77: B | I77: B | J77: CD 2A | K77: 286205 | L77: De 250 mil a 500 mil | M77: 348051 | N77: De 250 mil a 500 mil | O77: 368195 | P77: De 250 mil a 500 mil | Q77: Sim | R77: Sim | S77: Sim | T77: 2024 | U77: Sim | V77: Lei Municipal | W77: 7657/2024 | X77: 45461 | Y77: https://cascavel.atende.net/cidadao/pagina/plano-de-mobilidade | Z77: N:\a. DEPARTAMENTOS\i. DEPLAN\2.CGARG\SIMU\Levantamento Planos de Mobilidade\Planos Municipais - exemplos\SUL\Paraná\Cascavel_PR | AB77: Nao | AD77: Pemob 2025 | AE77: 45908 | AF77: Larissa Karla Boeing da Silva | AG77: Sim | AH77: Sim | AI77: Sim
A78: 3516200 | B78: SE | C78: SP | D78: Franca | E78: AU de Franca (SP) | F78: Não | G78: Nao | H78: B | I78: B | J78: CD 2A | K78: 318640 | L78: De 250 mil a 500 mil | M78: 352536 | N78: De 250 mil a 500 mil | O78: 365494 | P78: De 250 mil a 500 mil | Q78: Sim | R78: Sim | S78: Sim | T78: 2019 | U78: Sim | V78: Lei Municipal | W78: 314/2019 | X78: 43571 | Y78: https://leismunicipais.com.br/a2/sp/f/franca/lei-complementar/2019/32/319/lei-complementar-n-319-2019-altera-a-lei-n-2046-72-plano-diretor-fisico-do-municipio-de-franca-e-lei-complementar-n-137-2008-e-da-outras-providencias?q=319 | Z78: \\londrina\SNTMU$\a. DEPARTAMENTOS\i. DEPLAN\2.CGARG\SIMU\Levantamento Planos de Mobilidade 2019\Planos Municipais - exemplos\SUDESTE\São Paulo\Franca_SP | AB78: Nao | AD78: Pemob 2024 | AE78: 45497 | AG78: Sim | AH78: Sim | AI78: Sim
A79: 2610707 | B79: NE | C79: PE | D79: Paulista | E79: RM de Recife (PE) | F79: Sim | G79: Sim | H79: C | I79: C | J79: CD 1B | K79: 300466 | L79: De 250 mil a 500 mil | M79: 342167 | N79: De 250 mil a 500 mil | O79: 365144 | P79: De 250 mil a 500 mil | Q79: Sim | R79: Sim | S79: Nao | U79: Nao possui plano | V79: Nao possui plano | X79: Nao possui plano | AB79: Sim | AC79: 42705 | AD79: Ofício nº 10/2016 | AE79: 42507 | AG79: Sim | AH79: Sim | AI79: Sim
A80: 2609600 | B80: NE | C80: PE | D80: Olinda | E80: RM de Recife (PE) | F80: Sim | G80: Sim | H80: B | I80: B | J80: CD 1B | K80: 377779 | L80: De 250 mil a 500 mil | M80: 349976 | N80: De 250 mil a 500 mil | O80: 364717 | P80: De 250 mil a 500 mil | Q80: Sim | R80: Sim | S80: Sim | T80: 2018 | U80: Sim | V80: Lei Municipal | W80: 6064/2018 | X80: 43453 | Y80: www.plamob.olinda.pe.gov.br | Z80: L:\a. DEPARTAMENTOS\i. DEPLAN\2.CGARG\SIMU\Levantamento Planos de Mobilidade 2019\Planos Municipais - exemplos\NORDESTE\Olinda_PE | AB80: Nao | AD80: Ramson WhatsApp | AE80: 44691 | AG80: Sim | AH80: Sim | AI80: Sim
A81: 1506807 | B81: N | C81: PA | D81: Santarém | E81: RM de Santarém (PA) | F81: Não | G81: Nao | H81: B | I81: #N/A | J81: CD 2C | K81: 294580 | L81: De 250 mil a 500 mil | M81: 331942 | N81: De 250 mil a 500 mil | O81: 360871 | P81: De 250 mil a 500 mil | Q81: Sim | R81: Sim | S81: Sim | T81: 2022 | U81: Sim | V81: Decreto Municipal | W81: 817/2022 | X81: 44911 | Y81: https://drive.google.com/file/d/1bheI9xf7z0wbACAqIxPY11ROnFgORCgX/view https://drive.google.com/file/d/11kUmXkFROEGxOAJ-079PydiNGP5rCqm6/view https://transparencia.santarem.pa.gov.br/storage/attachments/decreto-no-8172022-gappms-de-16-de-dezembro-de-2022-64a58165c4a07.pdf | Z81: N:\a. DEPARTAMENTOS\i. DEPLAN\2.CGARG\SIMU\Levantamento Planos de Mobilidade\Planos Municipais - exemplos\NORTE\Santarém_PA | AB81: Nao | AD81: Email | AE81: 45138 | AF81: planejamento.smt@gmail.com smt@santarem.pa.gov.br reginaldopabreu@gmail.com | AG81: Sim | AH81: Sim | AI81: Sim
A82: 4304606 | B82: S | C82: RS | D82: Canoas | E82: RM de Porto Alegre (RS) | F82: Sim | G82: Sim | H82: #N/A | I82: #N/A | J82: CD 1A | K82: 323827 | L82: De 250 mil a 500 mil | M82: 347657 | N82: De 250 mil a 500 mil | O82: 359840 | P82: De 250 mil a 500 mil | Q82: Sim | R82: Sim | S82: Sim | T82: 2022 | U82: Sim | V82: Lei Municipal | W82: 6551/2022 | X82: 44663 | Z82: N:\a. DEPARTAMENTOS\i. DEPLAN\2.CGARG\SIMU\Levantamento Planos de Mobilidade\Planos Municipais - exemplos\SUL\Rio Grande do Sul\Canoas_RS | AB82: Nao | AD82: Contato Telefônico | AE82: 44706 | AF82: leticia.correa@canoas.rs.gov.br | AG82: Sim | AH82: Sim | AI82: Sim
A83: 3170107 | B83: SE | C83: MG | D83: Uberaba | E83: #N/A | F83: Não | G83: Nao | H83: B | I83: B | J83: CD 2C | K83: 295988 | L83: De 250 mil a 500 mil | M83: 337836 | N83: De 250 mil a 500 mil | O83: 356781 | P83: De 250 mil a 500 mil | Q83: Sim | R83: Sim | S83: Sim | T83: 2022 | U83: Nao | V83: Nao aprovado em lei | X83: Nao aprovado em lei | Z83: N:\a. DEPARTAMENTOS\i. DEPLAN\2.CGARG\SIMU\Levantamento Planos de Mobilidade\Planos Municipais - exemplos\SUDESTE\Minas Gerais\Uberaba_MG | AB83: Nao | AD83: Email | AE83: 44776 | AF83: juridicosds.uberaba@gmail.com; Oficio 779/2022 | AG83: Sim | AH83: Sim | AI83: Sim
A84: 4125506 | B84: S | C84: PR | D84: São José dos Pinhais | E84: RM de Curitiba (PR) | F84: Sim | G84: Sim | H84: B | I84: B | J84: CD 1B | K84: 264210 | L84: De 250 mil a 500 mil | M84: 329628 | N84: De 250 mil a 500 mil | O84: 349880 | P84: De 250 mil a 500 mil | Q84: Sim | R84: Sim | S84: Sim | T84: 2022 | U84: Nao | V84: Nao aprovado em lei | X84: Nao aprovado em lei | Z84: N:\a. DEPARTAMENTOS\i. DEPLAN\2.CGARG\SIMU\Levantamento Planos de Mobilidade\Planos Municipais - exemplos\SUL\Paraná\São José dos Pinhais_PR | AB84: Nao | AD84: Email | AE84: 44775 | AF84: ketlin.volcov@sjp.pr.gov.br; Oficio 476/2022 | AG84: Sim | AH84: Sim | AI84: Sim
A85: 3154606 | B85: SE | C85: MG | D85: Ribeirão das Neves | E85: RM de Belo Horizonte (MG) | F85: Sim | G85: Sim | H85: #N/A | I85: #N/A | J85: CD 1B | K85: 296317 | L85: De 250 mil a 500 mil | M85: 329794 | N85: De 250 mil a 500 mil | O85: 346971 | P85: De 250 mil a 500 mil | Q85: Sim | R85: Sim | S85: Sim | T85: 2024 | U85: Sim | V85: Lei Municipal | W85: 4508/2024 | X85: 45649 | AB85: Sim | AC85: Sem previsao | AD85: E-mail | AE85: 45652 | AF85: secplan@ribeiraodasneves.mg.gov.br | AG85: Sim | AH85: Sim | AI85: Sim
A86: 3205309 | B86: SE | C86: ES | D86: Vitória | E86: RM da Grande Vitória (ES) | F86: Sim | G86: Sim | H86: A | I86: A | J86: CD 1A | K86: 327801 | L86: De 250 mil a 500 mil | M86: 322869 | N86: De 250 mil a 500 mil | O86: 343378 | P86: De 250 mil a 500 mil | Q86: Sim | R86: Sim | S86: Sim | T86: 2008 | U86: Nao | V86: Nao aprovado em lei | X86: Nao aprovado em lei | Z86: L:\a. DEPARTAMENTOS\i. DEPLAN\2.CGARG\SIMU\Levantamento Planos de Mobilidade 2019\Planos Municipais - exemplos\SUDESTE\Espírito Santo\Vitória_ES | AB86: Nao | AD86: Ofício nº 907/2014 | AE86: 42136 | AG86: Sim | AH86: Sim | AI86: Sim
A87: 3551009 | B87: SE | C87: SP | D87: São Vicente | E87: RM da Baixada Santista (SP) | F87: Sim | G87: Sim | H87: B | I87: B | J87: CD 1A | K87: 332445 | L87: De 250 mil a 500 mil | M87: 329911 | N87: De 250 mil a 500 mil | O87: 338326 | P87: De 250 mil a 500 mil | Q87: Sim | R87: Sim | S87: Sim | T87: 2022 | U87: Sim | V87: Lei Municipal | W87: 4262/2022 | X87: 44652 | Z87: N:\a. DEPARTAMENTOS\i. DEPLAN\2.CGARG\SIMU\Levantamento Planos de Mobilidade\Planos Municipais - exemplos\SUDESTE\São Paulo\São Vicente_SP | AB87: Nao | AD87: Email | AE87: 44663 | AF87: FNP prefeito@saovicente.sp.gov.br | AG87: Sim | AH87: Sim | AI87: Sim
A88: 4314407 | B88: S | C88: RS | D88: Pelotas | E88: AU do Sul (RS) | F88: Não | G88: Nao | H88: B | I88: B | J88: CD 2A | K88: 328275 | L88: De 250 mil a 500 mil | M88: 325685 | N88: De 250 mil a 500 mil | O88: 336150 | P88: De 250 mil a 500 mil | Q88: Sim | R88: Sim | S88: Sim | T88: 2019 | U88: Sim | V88: Decreto Municipal | W88: 6209/2019 | X88: 43727 | Y88: http://www.pelotas.rs.gov.br/plano-mobilidade | Z88: L:\a. DEPARTAMENTOS\i. DEPLAN\2.CGARG\SIMU\Levantamento Planos de Mobilidade\Planos Municipais - exemplos\SUL\Rio Grande do Sul\Pelotas_RS | AB88: Nao | AD88: Pemob/2019 | AG88: Sim | AH88: Sim | AI88: Sim
A89: 3505708 | B89: SE | C89: SP | D89: Barueri | E89: RM de São Paulo (SP) | F89: Sim | G89: Sim | H89: #N/A | I89: #N/A | J89: CD 1A | K89: 240749 | L89: De 100 a 250 mil | M89: 316473 | N89: De 250 mil a 500 mil | O89: 333737 | P89: De 250 mil a 500 mil | Q89: Sim | R89: Sim | S89: Sim | T89: 2022 | U89: Nao | V89: Nao aprovado em lei | X89: Nao aprovado em lei | Z89: N:\a. DEPARTAMENTOS\i. DEPLAN\2.CGARG\SIMU\Levantamento Planos de Mobilidade\Planos Municipais - exemplos\SUDESTE\São Paulo\Barueri_SP | AB89: Nao respondeu | AD89: Email | AE89: 44778 | AF89: semurb.chefe.gabinete@barueri.sp.gov.br | AG89: Sim | AH89: Sim | AI89: Sim
A90: 1721000 | B90: N | C90: TO | D90: Palmas | E90: RM de Palmas (TO) | F90: Não | G90: Nao | H90: A | I90: A | J90: CD 2C | K90: 228332 | L90: De 100 a 250 mil | M90: 302692 | N90: De 250 mil a 500 mil | O90: 328499 | P90: De 250 mil a 500 mil | Q90: Sim | R90: Sim | S90: Sim | T90: 2024 | U90: Sim | V90: Decreto Municipal | W90: 2618/2024 | X90: 45643 | Z90: L:\a. DEPARTAMENTOS\i. DEPLAN\2.CGARG\SIMU\Levantamento Planos de Mobilidade 2019\Planos Municipais - exemplos\NORTE\Palmas_TO | AB90: Nao | AD90: Email | AE90: 45644 | AF90: gabsesmu@gmail.com; OFÍCIO Nº 358/2024 - STT/SESMU | AG90: Sim | AH90: Sim | AI90: Sim
A91: 3554102 | B91: SE | C91: SP | D91: Taubaté | E91: RM do Vale do Paraíba e Litoral Norte (SP) | F91: Não | G91: Nao | H91: B | I91: B | J91: CD 1A | K91: 278686 | L91: De 250 mil a 500 mil | M91: 310739 | N91: De 250 mil a 500 mil | O91: 322397 | P91: De 250 mil a 500 mil | Q91: Sim | R91: Sim | S91: Sim | T91: 2021 | U91: Sim | V91: Lei Municipal | W91: 5668/2021 | X91: 44516 | Y91: https://taubate.sp.gov.br/anexos/leis/2021/5668%20PLANO%20DE%20MOBILIDADE%20URBANA.pdf | Z91: \\londrina\SNTMU$\a. DEPARTAMENTOS\i. DEPLAN\2.CGARG\SIMU\Levantamento Planos de Mobilidade 2019\Planos Municipais - exemplos\SUDESTE\São Paulo\Taubaté_SP | AB91: Nao | AD91: Pemob 2024 | AE91: 45499 | AG91: Sim | AH91: Sim | AI91: Sim
A92: 2905701 | B92: NE | C92: BA | D92: Camaçari | E92: RM de Salvador (BA) | F92: Sim | G92: Sim | H92: B | I92: B | J92: CD 1B | K92: 242970 | L92: De 100 a 250 mil | M92: 300372 | N92: De 250 mil a 500 mil | O92: 321636 | P92: De 250 mil a 500 mil | Q92: Sim | R92: Sim | S92: Sim | T92: 2016 | U92: Nao | V92: Nao aprovado em lei | X92: Nao aprovado em lei | Y92: http://sedur.camacari.ba.gov.br/portal/plamob.php | Z92: L:\a. DEPARTAMENTOS\i. DEPLAN\2.CGARG\SIMU\Levantamento Planos de Mobilidade\Planos Municipais - exemplos\NORDESTE\Camaçari_BA | AB92: Sim | AC92: Sem previsao | AD92: Pemob 2018 | AE92: 43434 | AF92: Pemob 2018 | AG92: Sim | AH92: Sim | AI92: Sim
A93: 3552502 | B93: SE | C93: SP | D93: Suzano | E93: RM de São Paulo (SP) | F93: Sim | G93: Sim | H93: C | I93: #N/A | J93: CD 1B | K93: 262480 | L93: De 250 mil a 500 mil | M93: 307429 | N93: De 250 mil a 500 mil | O93: 320261 | P93: De 250 mil a 500 mil | Q93: Sim | R93: Sim | S93: Sim | T93: 2019 | U93: Sim | V93: Lei Municipal | W93: 5190/2019 | X93: 43616 | Y93: http://suzano.sp.gov.br/web/wp-content/uploads/2019/07/5190-19-PL-de-Mobilidade-Urbana.pdf | AB93: Nao | AD93: Ofício nº 21/2019 | AE93: 43686 | AF93: Pesquisa PlanMob 2019 | AG93: Sim | AH93: Sim | AI93: Sim
A94: 5108402 | B94: CO | C94: MT | D94: Várzea Grande | E94: RM do Vale do Rio Cuiabá (MT) | F94: Não | G94: Nao | H94: B | I94: B | J94: CD 1B | K94: 252596 | L94: De 250 mil a 500 mil | M94: 300078 | N94: De 250 mil a 500 mil | O94: 318922 | P94: De 250 mil a 500 mil | Q94: Sim | R94: Nao | S94: Nao respondeu | U94: Nao respondeu | V94: Nao respondeu | X94: Nao respondeu | AB94: Nao respondeu | AG94: Sim | AH94: Sim | AI94: Sim
A95: 1505536 | B95: N | C95: PA | D95: Parauapebas | E95: #N/A | F95: Não | G95: Nao | H95: B | I95: B | J95: CD 2C | K95: 153908 | L95: De 100 a 250 mil | M95: 267836 | N95: De 250 mil a 500 mil | O95: 305771 | P95: De 250 mil a 500 mil | Q95: Sim | R95: Sim | S95: Sim | T95: 2023 | U95: Sim | V95: Lei Municipal | W95: 5368/2023 | X95: 45253 | AB95: Nao | AD95: Ofício nº 089/2025 | AE95: 45776 | AF95: planejamento.semsi@parauapebas.pa.gov.br | AG95: Sim | AH95: Sim | AI95: Sim
A96: 2307304 | B96: NE | C96: CE | D96: Juazeiro do Norte | E96: RM do Cariri (CE) | F96: Não | G96: Nao | H96: B | I96: B | J96: CD 2A | K96: 249939 | L96: De 100 a 250 mil | M96: 286120 | N96: De 250 mil a 500 mil | O96: 305531 | P96: De 250 mil a 500 mil | Q96: Sim | R96: Sim | S96: Nao | U96: Nao possui plano | V96: Nao possui plano | X96: Nao possui plano | AB96: Sim | AC96: 44866 | AD96: Ofício nº 907/2014 | AE96: 42093 | AF96: FNP | AG96: Sim | AH96: Sim | AI96: Sim
A97: 3526902 | B97: SE | C97: SP | D97: Limeira | E97: RM de Piracicaba (SP) | F97: Não | G97: Nao | H97: B | I97: B | J97: CD 2A | K97: 276022 | L97: De 250 mil a 500 mil | M97: 291869 | N97: De 250 mil a 500 mil | O97: 301292 | P97: De 250 mil a 500 mil | Q97: Sim | R97: Sim | S97: Sim | T97: 2020 | U97: Sim | V97: Lei Municipal | W97: 860/2020 | X97: 44106 | Z97: N:\a. DEPARTAMENTOS\i. DEPLAN\2.CGARG\SIMU\Levantamento Planos de Mobilidade\Planos Municipais - exemplos\SUDESTE\São Paulo\Limeira_SP | AB97: Nao | AD97: Email | AE97: 44774 | AF97: rodrigo.oliveira@limeira.sp.gov.br | AG97: Sim | AH97: Sim | AI97: Sim
A98: 4108304 | B98: S | C98: PR | D98: Foz do Iguaçu | E98: #N/A | F98: Não | G98: Nao | H98: A | I98: A | J98: CD 2A | K98: 256088 | L98: De 250 mil a 500 mil | M98: 285415 | N98: De 250 mil a 500 mil | O98: 297352 | P98: De 250 mil a 500 mil | Q98: Sim | R98: Sim | S98: Sim | T98: 2018 | U98: Sim | V98: Decreto Municipal | W98: 26.312/2018 | X98: 43213 | Z98: L:\a. DEPARTAMENTOS\i. DEPLAN\2.CGARG\SIMU\Levantamento Planos de Mobilidade\Planos Municipais - exemplos\SUL\Paraná\Foz do Iguaçú | AB98: Nao | AD98: Pemob/2019 | AG98: Sim | AH98: Sim | AI98: Sim
A99: 4216602 | B99: S | C99: SC | D99: São José | E99: RM de Florianópolis (SC) | F99: Sim | G99: Sim | H99: #N/A | I99: #N/A | J99: CD 1B | K99: 209804 | L99: De 100 a 250 mil | M99: 270299 | N99: De 250 mil a 500 mil | O99: 295658 | P99: De 250 mil a 500 mil | Q99: Sim | R99: Sim | S99: Nao | U99: Nao possui plano | V99: Nao possui plano | X99: Nao possui plano | AB99: Nao | AD99: Ofício nº 21/2019 | AE99: 43609 | AF99: Pesquisa PlanMob 2019 | AG99: Sim | AH99: Sim | AI99: Sim
A100: 3303906 | B100: SE | C100: RJ | D100: Petrópolis | E100: RM do Rio de Janeiro (RJ) | F100: Sim | G100: Nao | H100: A | I100: A | J100: CD 2A | K100: 295917 | L100: De 250 mil a 500 mil | M100: 278881 | N100: De 250 mil a 500 mil | O100: 294926 | P100: De 250 mil a 500 mil | Q100: Sim | R100: Sim | S100: Sim | T100: 2019 | U100: Sim | V100: Decreto Municipal | W100: 721/2019 | X100: 43566 | Y100: http://web2.petropolis.rj.gov.br/cptrans/phocadownload/plano-de-mobilidade/PlanMob%20Petropolis%202019-2029%20Versao%20Interativa%20Completa.pdf | Z100: L:\a. DEPARTAMENTOS\i. DEPLAN\2.CGARG\SIMU\Levantamento Planos de Mobilidade\Planos Municipais - exemplos\SUDESTE\Rio de Janeiro\Petrópolis | AB100: Nao | AD100: Ofício nº 13/2019 | AE100: 43616 | AF100: FNP | AG100: Sim | AH100: Sim | AI100: Sim
...

Sheet RMs
A1: UF | B1: RM | C1: Censo 2010 | D1: Censo 2022 | E1: Estimativa 2025 | H1: Censo 2010 | I1: Censo 2022 | J1: Estimativa 2025
A2: SP | B2: RM de São Paulo (SP) | C2: =SUMIF(Levantamento!$E$2:$E$5572,B2,Levantamento!$K$2:$K$5572) -> 19683975 | D2: =SUMIF(Levantamento!$E$2:$E$5572,B2,Levantamento!$M$2:$M$5572) -> 20731920 | E2: =SUMIF(Levantamento!$E$2:$E$5572,B2,Levantamento!$O$2:$O$5572) -> 21555260 | H2: =SUMIFS(Levantamento!$K$2:$K$5572,Levantamento!$E$2:$E$5572,B2,Levantamento!$G$2:$G$5572,"Sim") -> 18724542 | I2: =SUMIFS(Levantamento!$M$2:$M$5572,Levantamento!$E$2:$E$5572,B2,Levantamento!$G$2:$G$5572,"Sim") -> 19672108 | J2: =SUMIFS(Levantamento!$O$2:$O$5572,Levantamento!$E$2:$E$5572,B2,Levantamento!$G$2:$G$5572,"Sim") -> 20456622
A3: RJ | B3: RM do Rio de Janeiro (RJ) | C3: =SUMIF(Levantamento!$E$2:$E$5572,B3,Levantamento!$K$2:$K$5572) -> 12241449 | D3: =SUMIF(Levantamento!$E$2:$E$5572,B3,Levantamento!$M$2:$M$5572) -> 12021871 | E3: =SUMIF(Levantamento!$E$2:$E$5572,B3,Levantamento!$O$2:$O$5572) -> 12937950 | H3: =SUMIFS(Levantamento!$K$2:$K$5572, Levantamento!$E$2:$E$5572,B3, Levantamento!$G$2:$G$5572,"Sim") -> 11119113 | I3: =SUMIFS(Levantamento!$M$2:$M$5572,Levantamento!$E$2:$E$5572,B3,Levantamento!$G$2:$G$5572,"Sim") -> 10898794 | J3: =SUMIFS(Levantamento!$O$2:$O$5572,Levantamento!$E$2:$E$5572,B3,Levantamento!$G$2:$G$5572,"Sim") -> 11747297
A4: MG | B4: RM de Belo Horizonte (MG) | C4: =SUMIF(Levantamento!$E$2:$E$5572,B4,Levantamento!$K$2:$K$5572) -> 4883970 | D4: =SUMIF(Levantamento!$E$2:$E$5572,B4,Levantamento!$M$2:$M$5572) -> 5128282 | E4: =SUMIF(Levantamento!$E$2:$E$5572,B4,Levantamento!$O$2:$O$5572) -> 5383386 | H4: =SUMIFS(Levantamento!$K$2:$K$5572,Levantamento!$E$2:$E$5572,B4,Levantamento!$G$2:$G$5572,"Sim") -> 4326689 | I4: =SUMIFS(Levantamento!$M$2:$M$5572,Levantamento!$E$2:$E$5572,B4,Levantamento!$G$2:$G$5572,"Sim") -> 4438830 | J4: =SUMIFS(Levantamento!$O$2:$O$5572,Levantamento!$E$2:$E$5572,B4,Levantamento!$G$2:$G$5572,"Sim") -> 4650076
A5: RS | B5: RM de Porto Alegre (RS) | C5: =SUMIF(Levantamento!$E$2:$E$5572,B5,Levantamento!$K$2:$K$5572) -> 4032062 | D5: =SUMIF(Levantamento!$E$2:$E$5572,B5,Levantamento!$M$2:$M$5572) -> 4019420 | E5: =SUMIF(Levantamento!$E$2:$E$5572,B5,Levantamento!$O$2:$O$5572) -> 4167509 | H5: =SUMIFS(Levantamento!$K$2:$K$5572,Levantamento!$E$2:$E$5572,B5,Levantamento!$G$2:$G$5572,"Sim") -> 3206912 | I5: =SUMIFS(Levantamento!$M$2:$M$5572,Levantamento!$E$2:$E$5572,B5,Levantamento!$G$2:$G$5572,"Sim") -> 3146560 | J5: =SUMIFS(Levantamento!$O$2:$O$5572,Levantamento!$E$2:$E$5572,B5,Levantamento!$G$2:$G$5572,"Sim") -> 3267880
A6: CE | B6: RM de Fortaleza (CE) | C6: =SUMIF(Levantamento!$E$2:$E$5572,B6,Levantamento!$K$2:$K$5572) -> 3741198 | D6: =SUMIF(Levantamento!$E$2:$E$5572,B6,Levantamento!$M$2:$M$5572) -> 3905891 | E6: =SUMIF(Levantamento!$E$2:$E$5572,B6,Levantamento!$O$2:$O$5572) -> 4154961 | H6: =SUMIFS(Levantamento!$K$2:$K$5572,Levantamento!$E$2:$E$5572,B6,Levantamento!$G$2:$G$5572,"Sim") -> 3291204 | I6: =SUMIFS(Levantamento!$M$2:$M$5572,Levantamento!$E$2:$E$5572,B6,Levantamento!$G$2:$G$5572,"Sim") -> 3360328 | J6: =SUMIFS(Levantamento!$O$2:$O$5572,Levantamento!$E$2:$E$5572,B6,Levantamento!$G$2:$G$5572,"Sim") -> 3571020
A7: PE | B7: RM de Recife (PE) | C7: =SUMIF(Levantamento!$E$2:$E$5572,B7,Levantamento!$K$2:$K$5572) -> 3690547 | D7: =SUMIF(Levantamento!$E$2:$E$5572,B7,Levantamento!$M$2:$M$5572) -> 3726974 | E7: =SUMIF(Levantamento!$E$2:$E$5572,B7,Levantamento!$O$2:$O$5572) -> 3961730 | H7: =SUMIFS(Levantamento!$K$2:$K$5572,Levantamento!$E$2:$E$5572,B7,Levantamento!$G$2:$G$5572,"Sim") -> 3489405 | I7: =SUMIFS(Levantamento!$K$2:$K$5572,Levantamento!$E$2:$E$5572,B7,Levantamento!$G$2:$G$5572,"Sim") -> 3489405 | J7: =SUMIFS(Levantamento!$O$2:$O$5572,Levantamento!$E$2:$E$5572,B7,Levantamento!$G$2:$G$5572,"Sim") -> 3722214
A8: PR | B8: RM de Curitiba (PR) | C8: =SUMIF(Levantamento!$E$2:$E$5572,B8,Levantamento!$K$2:$K$5572) -> 3223836 | D8: =SUMIF(Levantamento!$E$2:$E$5572,B8,Levantamento!$M$2:$M$5572) -> 3560258 | E8: =SUMIF(Levantamento!$E$2:$E$5572,B8,Levantamento!$O$2:$O$5572) -> 3720170 | H8: =SUMIFS(Levantamento!$K$2:$K$5572,Levantamento!$E$2:$E$5572,B8,Levantamento!$G$2:$G$5572,"Sim") -> 2855678 | I8: =SUMIFS(Levantamento!$M$2:$M$5572,Levantamento!$E$2:$E$5572,B8,Levantamento!$G$2:$G$5572,"Sim") -> 3137998 | J8: =SUMIFS(Levantamento!$O$2:$O$5572,Levantamento!$E$2:$E$5572,B8,Levantamento!$G$2:$G$5572,"Sim") -> 3279590
A9: BA | B9: RM de Salvador (BA) | C9: =SUMIF(Levantamento!$E$2:$E$5572,B9,Levantamento!$K$2:$K$5572) -> 3573973 | D9: =SUMIF(Levantamento!$E$2:$E$5572,B9,Levantamento!$M$2:$M$5572) -> 3415022 | E9: =SUMIF(Levantamento!$E$2:$E$5572,B9,Levantamento!$O$2:$O$5572) -> 3623330 | H9: =SUMIFS(Levantamento!$K$2:$K$5572,Levantamento!$E$2:$E$5572,B9,Levantamento!$G$2:$G$5572,"Sim") -> 3220847 | I9: =SUMIFS(Levantamento!$M$2:$M$5572,Levantamento!$E$2:$E$5572,B9,Levantamento!$G$2:$G$5572,"Sim") -> 3055729 | J9: =SUMIFS(Levantamento!$O$2:$O$5572,Levantamento!$E$2:$E$5572,B9,Levantamento!$G$2:$G$5572,"Sim") -> 3246176
A10: DF | B10: RIDE do Distrito Federal e Entorno | C10: =SUMIF(Levantamento!$E$2:$E$5572,B10,Levantamento!$K$2:$K$5572)+SUMIF(Levantamento!$E$2:$E$5572,"RIDE do Distrito Federal e Entorno_RM do Entorno do Distrito Federal",Levantamento!$K$2:$K$5572) -> 2956360 | D10: =SUMIF(Levantamento!$E$2:$E$5572,B10,Levantamento!$M$2:$M$5572)+SUMIF(Levantamento!$E$2:$E$5572,"RIDE do Distrito Federal e Entorno_RM do Entorno do Distrito Federal",Levantamento!$M$2:$M$5572) -> 3239483 | E10: =SUMIF(Levantamento!$E$2:$E$5572,B10,Levantamento!$O$2:$O$5572)+SUMIF(Levantamento!$E$2:$E$5572,"RIDE do Distrito Federal e Entorno_RM do Entorno do Distrito Federal",Levantamento!$O$2:$O$5572) -> 3434812 | H10: =SUMIFS(Levantamento!$K$2:$K$5572,Levantamento!$E$2:$E$5572,B10,Levantamento!$G$2:$G$5572,"Sim")+SUMIFS(Levantamento!$K$2:$K$5572,Levantamento!$E$2:$E$5572,"RIDE do Distrito Federal e Entorno_RM do Entorno do Distrito Federal",Levantamento!$G$2:$G$5572,"Sim") -> 2570160 | I10: =SUMIFS(Levantamento!$M$2:$M$5572,Levantamento!$E$2:$E$5572,B10,Levantamento!$G$2:$G$5572,"Sim")+SUMIFS(Levantamento!$M$2:$M$5572,Levantamento!$E$2:$E$5572,"RIDE do Distrito Federal e Entorno_RM do Entorno do Distrito Federal",Levantamento!$G$2:$G$5572,"Sim") -> 2817381 | J10: =SUMIFS(Levantamento!$O$2:$O$5572,Levantamento!$E$2:$E$5572,B10,Levantamento!$G$2:$G$5572,"Sim")+SUMIFS(Levantamento!$O$2:$O$5572,Levantamento!$E$2:$E$5572,"RIDE do Distrito Federal e Entorno_RM do Entorno do Distrito Federal",Levantamento!$G$2:$G$5572,"Sim") -> 2996899
A11: SP | B11: RM de Campinas (SP) | C11: =SUMIF(Levantamento!$E$2:$E$5572,B11,Levantamento!$K$2:$K$5572) -> 2808906 | D11: =SUMIF(Levantamento!$E$2:$E$5572,B11,Levantamento!$M$2:$M$5572) -> 3178601 | E11: =SUMIF(Levantamento!$E$2:$E$5572,B11,Levantamento!$O$2:$O$5572) -> 3317498 | H11: =SUMIFS(Levantamento!$K$2:$K$5572,Levantamento!$E$2:$E$5572,B11,Levantamento!$G$2:$G$5572,"Sim") -> 2208555 | I11: =SUMIFS(Levantamento!$M$2:$M$5572,Levantamento!$E$2:$E$5572,B11,Levantamento!$G$2:$G$5572,"Sim") -> 2451289 | J11: =SUMIFS(Levantamento!$O$2:$O$5572,Levantamento!$E$2:$E$5572,B11,Levantamento!$G$2:$G$5572,"Sim") -> 2557576
A12: GO | B12: RM de Goiânia (GO) | C12: =SUMIF(Levantamento!$E$2:$E$5572,B12,Levantamento!$K$2:$K$5572) -> 2178892 | D12: =SUMIF(Levantamento!$E$2:$E$5572,B12,Levantamento!$M$2:$M$5572) -> 2600936 | E12: =SUMIF(Levantamento!$E$2:$E$5572,B12,Levantamento!$O$2:$O$5572) -> 2754016 | H12: =SUMIFS(Levantamento!$K$2:$K$5572,Levantamento!$E$2:$E$5572,B12,Levantamento!$G$2:$G$5572,"Sim") -> 1980649 | I12: =SUMIFS(Levantamento!$M$2:$M$5572,Levantamento!$E$2:$E$5572,B12,Levantamento!$G$2:$G$5572,"Sim") -> 2335144 | J12: =SUMIFS(Levantamento!$O$2:$O$5572,Levantamento!$E$2:$E$5572,B12,Levantamento!$G$2:$G$5572,"Sim") -> 2469374
A13: AM | B13: RM de Manaus (AM) | C13: =SUMIF(Levantamento!$E$2:$E$5572,B13,Levantamento!$K$2:$K$5572) -> 2210647 | D13: =SUMIF(Levantamento!$E$2:$E$5572,B13,Levantamento!$M$2:$M$5572) -> 2532519 | E13: =SUMIF(Levantamento!$E$2:$E$5572,B13,Levantamento!$O$2:$O$5572) -> 2811884 | H13: =SUMIFS(Levantamento!$K$2:$K$5572,Levantamento!$E$2:$E$5572,B13,Levantamento!$G$2:$G$5572,"Sim") -> 1802014 | I13: =SUMIFS(Levantamento!$M$2:$M$5572,Levantamento!$E$2:$E$5572,B13,Levantamento!$G$2:$G$5572,"Sim") -> 2063689 | J13: =SUMIFS(Levantamento!$O$2:$O$5572,Levantamento!$E$2:$E$5572,B13,Levantamento!$G$2:$G$5572,"Sim") -> 2303732
A14: SP | B14: RM do Vale do Paraíba e Litoral Norte (SP) | C14: =SUMIF(Levantamento!$E$2:$E$5572,B14,Levantamento!$K$2:$K$5572) -> 2264594 | D14: =SUMIF(Levantamento!$E$2:$E$5572,B14,Levantamento!$M$2:$M$5572) -> 2505723 | E14: =SUMIF(Levantamento!$E$2:$E$5572,B14,Levantamento!$O$2:$O$5572) -> 2601680
A15: PA | B15: RM de Belém (PA) | C15: =SUMIF(Levantamento!$E$2:$E$5572,B15,Levantamento!$K$2:$K$5572) -> 2374891 | D15: =SUMIF(Levantamento!$E$2:$E$5572,B15,Levantamento!$M$2:$M$5572) -> 2370545 | E15: =SUMIF(Levantamento!$E$2:$E$5572,B15,Levantamento!$O$2:$O$5572) -> 2544868 | H15: =SUMIFS(Levantamento!$K$2:$K$5572,Levantamento!$E$2:$E$5572,B15,Levantamento!$G$2:$G$5572,"Sim") -> 2025276 | I15: =SUMIFS(Levantamento!$M$2:$M$5572,Levantamento!$E$2:$E$5572,B15,Levantamento!$G$2:$G$5572,"Sim") -> 1957533 | J15: =SUMIFS(Levantamento!$O$2:$O$5572,Levantamento!$E$2:$E$5572,B15,Levantamento!$G$2:$G$5572,"Sim") -> 2094941
A16: SP | B16: RM de Sorocaba (SP) | C16: =SUMIF(Levantamento!$E$2:$E$5572,B16,Levantamento!$K$2:$K$5572) -> 1871162 | D16: =SUMIF(Levantamento!$E$2:$E$5572,B16,Levantamento!$M$2:$M$5572) -> 2174525 | E16: =SUMIF(Levantamento!$E$2:$E$5572,B16,Levantamento!$O$2:$O$5572) -> 2268579
A17: ES | B17: RM da Grande Vitória (ES) | C17: =SUMIF(Levantamento!$E$2:$E$5572,B17,Levantamento!$K$2:$K$5572) -> 1687704 | D17: =SUMIF(Levantamento!$E$2:$E$5572,B17,Levantamento!$M$2:$M$5572) -> 1880828 | E17: =SUMIF(Levantamento!$E$2:$E$5572,B17,Levantamento!$O$2:$O$5572) -> 2040329 | H17: =SUMIFS(Levantamento!$K$2:$K$5572,Levantamento!$E$2:$E$5572,B17,Levantamento!$G$2:$G$5572,"Sim") -> 1565393 | I17: =SUMIFS(Levantamento!$M$2:$M$5572,Levantamento!$E$2:$E$5572,B17,Levantamento!$G$2:$G$5572,"Sim") -> 1738158 | J17: =SUMIFS(Levantamento!$O$2:$O$5572,Levantamento!$E$2:$E$5572,B17,Levantamento!$G$2:$G$5572,"Sim") -> 1885120
A18: SP | B18: RM da Baixada Santista (SP) | C18: =SUMIF(Levantamento!$E$2:$E$5572,B18,Levantamento!$K$2:$K$5572) -> 1664136 | D18: =SUMIF(Levantamento!$E$2:$E$5572,B18,Levantamento!$M$2:$M$5572) -> 1805531 | E18: =SUMIF(Levantamento!$E$2:$E$5572,B18,Levantamento!$O$2:$O$5572) -> 1867558 | H18: =SUMIFS(Levantamento!$K$2:$K$5572,Levantamento!$E$2:$E$5572,B18,Levantamento!$G$2:$G$5572,"Sim") -> 1423368 | I18: =SUMIFS(Levantamento!$M$2:$M$5572,Levantamento!$E$2:$E$5572,B18,Levantamento!$G$2:$G$5572,"Sim") -> 1498564 | J18: =SUMIFS(Levantamento!$O$2:$O$5572,Levantamento!$E$2:$E$5572,B18,Levantamento!$G$2:$G$5572,"Sim") -> 1546153
A19: SP | B19: RM de Ribeirão Preto (SP) | C19: =SUMIF(Levantamento!$E$2:$E$5572,B19,Levantamento!$K$2:$K$5572) -> 1511140 | D19: =SUMIF(Levantamento!$E$2:$E$5572,B19,Levantamento!$M$2:$M$5572) -> 1648111 | E19: =SUMIF(Levantamento!$E$2:$E$5572,B19,Levantamento!$O$2:$O$5572) -> 1707166
A20: MA | B20: RM da Grande São Luís (MA) | C20: =SUMIF(Levantamento!$E$2:$E$5572,B20,Levantamento!$K$2:$K$5572) -> 1492370 | D20: =SUMIF(Levantamento!$E$2:$E$5572,B20,Levantamento!$M$2:$M$5572) -> 1646005 | E20: =SUMIF(Levantamento!$E$2:$E$5572,B20,Levantamento!$O$2:$O$5572) -> 1726262 | H20: =SUMIFS(Levantamento!$K$2:$K$5572,Levantamento!$E$2:$E$5572,B20,Levantamento!$G$2:$G$5572,"Sim") -> 1309330 | I20: =SUMIFS(Levantamento!$M$2:$M$5572,Levantamento!$E$2:$E$5572,B20,Levantamento!$G$2:$G$5572,"Sim") -> 1458836 | J20: =SUMIFS(Levantamento!$O$2:$O$5572,Levantamento!$E$2:$E$5572,B20,Levantamento!$G$2:$G$5572,"Sim") -> 1533693
A21: RN | B21: RM de Natal (RN) | C21: =SUMIF(Levantamento!$E$2:$E$5572,B21,Levantamento!$K$2:$K$5572) -> 1418461 | D21: =SUMIF(Levantamento!$E$2:$E$5572,B21,Levantamento!$M$2:$M$5572) -> 1527661 | E21: =SUMIF(Levantamento!$E$2:$E$5572,B21,Levantamento!$O$2:$O$5572) -> 1613858 | H21: =SUMIFS(Levantamento!$K$2:$K$5572,Levantamento!$E$2:$E$5572,B21,Levantamento!$G$2:$G$5572,"Sim") -> 1187899 | I21: =SUMIFS(Levantamento!$M$2:$M$5572,Levantamento!$E$2:$E$5572,B21,Levantamento!$G$2:$G$5572,"Sim") -> 1263738 | J21: =SUMIFS(Levantamento!$O$2:$O$5572,Levantamento!$E$2:$E$5572,B21,Levantamento!$G$2:$G$5572,"Sim") -> 1336097
A22: SP | B22: RM de Piracicaba (SP) | C22: =SUMIF(Levantamento!$E$2:$E$5572,B22,Levantamento!$K$2:$K$5572) -> 1381339 | D22: =SUMIF(Levantamento!$E$2:$E$5572,B22,Levantamento!$M$2:$M$5572) -> 1519024 | E22: =SUMIF(Levantamento!$E$2:$E$5572,B22,Levantamento!$O$2:$O$5572) -> 1572980
A23: SC | B23: RM do Norte/Nordeste Catarinense (SC) | C23: =SUMIF(Levantamento!$E$2:$E$5572,B23,Levantamento!$K$2:$K$5572)+SUMIF(Levantamento!$E$2:$E$5572,"RM do Norte/Nordeste Catarinense (SC); RM de Joinville (SC)",Levantamento!$K$2:$K$5572)+SUMIF(Levantamento!$E$2:$E$5572,"RM do Norte/Nordeste Catarinense (SC); RM de Jaraguá do Sul (SC)",Levantamento!$K$2:$K$5572)+SUMIF(Levantamento!$E$2:$E$5572,"RM do Norte/Nordeste Catarinense (SC); RM do Planalto Norte (SC)",Levantamento!$K$2:$K$5572) -> 1222730 | D23: =SUMIF(Levantamento!$E$2:$E$5572,B23,Levantamento!$M$2:$M$5572)+SUMIF(Levantamento!$E$2:$E$5572,"RM do Norte/Nordeste Catarinense (SC); RM de Joinville (SC)",Levantamento!$M$2:$M$5572)+SUMIF(Levantamento!$E$2:$E$5572,"RM do Norte/Nordeste Catarinense (SC); RM de Jaraguá do Sul (SC)",Levantamento!$M$2:$M$5572)+SUMIF(Levantamento!$E$2:$E$5572,"RM do Norte/Nordeste Catarinense (SC); RM do Planalto Norte (SC)",Levantamento!$M$2:$M$5572) -> 1480750 | E23: =SUMIF(Levantamento!$E$2:$E$5572,B23,Levantamento!$O$2:$O$5572)+SUMIF(Levantamento!$E$2:$E$5572,"RM do Norte/Nordeste Catarinense (SC); RM de Joinville (SC)",Levantamento!$O$2:$O$5572)+SUMIF(Levantamento!$E$2:$E$5572,"RM do Norte/Nordeste Catarinense (SC); RM de Jaraguá do Sul (SC)",Levantamento!$O$2:$O$5572)+SUMIF(Levantamento!$E$2:$E$5572,"RM do Norte/Nordeste Catarinense (SC); RM do Planalto Norte (SC)",Levantamento!$O$2:$O$5572) -> 1593700
A24: SC | B24: RM de Florianópolis (SC) | C24: =SUMIF(Levantamento!$E$2:$E$5572,B24,Levantamento!$K$2:$K$5572) -> 1012233 | D24: =SUMIF(Levantamento!$E$2:$E$5572,B24,Levantamento!$M$2:$M$5572) -> 1356861 | E24: =SUMIF(Levantamento!$E$2:$E$5572,B24,Levantamento!$O$2:$O$5572) -> 1493879 | H24: =SUMIFS(Levantamento!$K$2:$K$5572,Levantamento!$E$2:$E$5572,B24,Levantamento!$G$2:$G$5572,"Sim") -> 826584 | I24: =SUMIFS(Levantamento!$M$2:$M$5572,Levantamento!$E$2:$E$5572,B24,Levantamento!$G$2:$G$5572,"Sim") -> 1106881 | J24: =SUMIFS(Levantamento!$O$2:$O$5572,Levantamento!$E$2:$E$5572,B24,Levantamento!$G$2:$G$5572,"Sim") -> 1220369
A25: PB | B25: RM de João Pessoa (PB) | C25: =SUMIF(Levantamento!$E$2:$E$5572,B25,Levantamento!$K$2:$K$5572) -> 1156273 | D25: =SUMIF(Levantamento!$E$2:$E$5572,B25,Levantamento!$M$2:$M$5572) -> 1304280 | E25: =SUMIF(Levantamento!$E$2:$E$5572,B25,Levantamento!$O$2:$O$5572) -> 1393026 | H25: =SUMIFS(Levantamento!$K$2:$K$5572,Levantamento!$E$2:$E$5572,B25,Levantamento!$G$2:$G$5572,"Sim") -> 1001485 | I25: =SUMIFS(Levantamento!$M$2:$M$5572,Levantamento!$E$2:$E$5572,B25,Levantamento!$G$2:$G$5572,"Sim") -> 1133103 | J25: =SUMIFS(Levantamento!$O$2:$O$5572,Levantamento!$E$2:$E$5572,B25,Levantamento!$G$2:$G$5572,"Sim") -> 1213081
A26: AL | B26: RM de Maceió (AL) | C26: =SUMIF(Levantamento!$E$2:$E$5572,B26,Levantamento!$K$2:$K$5572) -> 1227396 | D26: =SUMIF(Levantamento!$E$2:$E$5572,B26,Levantamento!$M$2:$M$5572) -> 1300609 | E26: =SUMIF(Levantamento!$E$2:$E$5572,B26,Levantamento!$O$2:$O$5572) -> 1348674 | H26: =SUMIFS(Levantamento!$K$2:$K$5572,Levantamento!$E$2:$E$5572,B26,Levantamento!$G$2:$G$5572,"Sim") -> 1015832 | I26: =SUMIFS(Levantamento!$M$2:$M$5572,Levantamento!$E$2:$E$5572,B26,Levantamento!$G$2:$G$5572,"Sim") -> 1076121 | J26: =SUMIFS(Levantamento!$O$2:$O$5572,Levantamento!$E$2:$E$5572,B26,Levantamento!$G$2:$G$5572,"Sim") -> 1117715
A27: PI_MA | B27: RIDE da Grande Teresina (PI/MA) | C27: =SUMIF(Levantamento!$E$2:$E$5572,B26,Levantamento!$K$2:$K$5572)+SUMIF(Levantamento!$E$2:$E$5572,"RIDE da Grande Teresina (PI/MA); RM da Zona Leste do Estado do Maranhão (MA)",Levantamento!$K$2:$K$5572) -> 1382856 | D27: =SUMIF(Levantamento!$E$2:$E$5572,B27,Levantamento!$M$2:$M$5572)+SUMIF(Levantamento!$E$2:$E$5572,"RIDE da Grande Teresina (PI/MA); RM da Zona Leste do Estado do Maranhão (MA)",Levantamento!$M$2:$M$5572) -> 1246608 | E27: =SUMIF(Levantamento!$E$2:$E$5572,B27,Levantamento!$O$2:$O$5572)+SUMIF(Levantamento!$E$2:$E$5572,"RIDE da Grande Teresina (PI/MA); RM da Zona Leste do Estado do Maranhão (MA)",Levantamento!$O$2:$O$5572) -> 1303288 | H27: =SUMIFS(Levantamento!$K$2:$K$5572,Levantamento!$E$2:$E$5572,B26,Levantamento!$G$2:$G$5572,"Sim")+SUMIFS(Levantamento!$K$2:$K$5572,Levantamento!$E$2:$E$5572,"RIDE da Grande Teresina (PI/MA); RM da Zona Leste do Estado do Maranhão (MA)",Levantamento!$G$2:$G$5572,"Sim") -> 1171292 | I27: =SUMIFS(Levantamento!$M$2:$M$5572,Levantamento!$E$2:$E$5572,B27,Levantamento!$G$2:$G$5572,"Sim")+SUMIFS(Levantamento!$M$2:$M$5572,Levantamento!$E$2:$E$5572,"RIDE da Grande Teresina (PI/MA); RM da Zona Leste do Estado do Maranhão (MA)",Levantamento!$G$2:$G$5572,"Sim") -> 1040765 | J27: =SUMIFS(Levantamento!$O$2:$O$5572,Levantamento!$E$2:$E$5572,B27,Levantamento!$G$2:$G$5572,"Sim")+SUMIFS(Levantamento!$O$2:$O$5572,Levantamento!$E$2:$E$5572,"RIDE da Grande Teresina (PI/MA); RM da Zona Leste do Estado do Maranhão (MA)",Levantamento!$G$2:$G$5572,"Sim") -> 1088403
A28: DF | B28: RM do Entorno do Distrito Federal | C28: =SUMIF(Levantamento!$E$2:$E$5572,B28,Levantamento!$K$2:$K$5572)+SUMIF(Levantamento!$E$2:$E$5572,"RIDE do Distrito Federal e Entorno; RM do Entorno do Distrito Federal",Levantamento!$K$2:$K$5572) -> 954464 | D28: =SUMIF(Levantamento!$E$2:$E$5572,B28,Levantamento!$M$2:$M$5572)+SUMIF(Levantamento!$E$2:$E$5572,"RIDE do Distrito Federal e Entorno; RM do Entorno do Distrito Federal",Levantamento!$M$2:$M$5572) -> 1244633 | E28: =SUMIF(Levantamento!$E$2:$E$5572,B28,Levantamento!$O$2:$O$5572)+SUMIF(Levantamento!$E$2:$E$5572,"RIDE do Distrito Federal e Entorno; RM do Entorno do Distrito Federal",Levantamento!$O$2:$O$5572) -> 1334577
A29: PR | B29: RM de Londrina (PR) | C29: =SUMIF(Levantamento!$E$2:$E$5572,B29,Levantamento!$K$2:$K$5572) -> 1000062 | D29: =SUMIF(Levantamento!$E$2:$E$5572,B29,Levantamento!$M$2:$M$5572) -> 1088734 | E29: =SUMIF(Levantamento!$E$2:$E$5572,B29,Levantamento!$O$2:$O$5572) -> 1131313
A30: MT | B30: RM do Vale do Rio Cuiabá (MT) | C30: =SUMIF(Levantamento!$E$2:$E$5572,B30,Levantamento!$K$2:$K$5572) -> 888692 | D30: =SUMIF(Levantamento!$E$2:$E$5572,B30,Levantamento!$M$2:$M$5572) -> 1047730 | E30: =SUMIF(Levantamento!$E$2:$E$5572,B30,Levantamento!$O$2:$O$5572) -> 1112753 | H30: =SUMIF(Levantamento!D2:D5572,Levantamento!D32,Levantamento!K2:K5572)+SUMIF(Levantamento!D2:D5572,Levantamento!D94,Levantamento!K2:K5572) -> 808030 | I30: =SUMIF(Levantamento!D2:D5572,Levantamento!D32,Levantamento!M2:M5572)+SUMIF(Levantamento!D2:D5572,Levantamento!D94,Levantamento!M2:M5572) -> 955372 | J30: =SUMIF(Levantamento!D2:D5572,Levantamento!D32,Levantamento!O2:O5572)+SUMIF(Levantamento!D2:D5572,Levantamento!D94,Levantamento!O2:O5572) -> 1015317
A31: SP | B31: RM de São José do Rio Preto (SP) | C31: =SUMIF(Levantamento!$E$2:$E$5572,B31,Levantamento!$K$2:$K$5572) -> 840133 | D31: =SUMIF(Levantamento!$E$2:$E$5572,B31,Levantamento!$M$2:$M$5572) -> 971097 | E31: =SUMIF(Levantamento!$E$2:$E$5572,B31,Levantamento!$O$2:$O$5572) -> 1010633
A32: SE | B32: RM de Aracaju (SE) | C32: =SUMIF(Levantamento!$E$2:$E$5572,B32,Levantamento!$K$2:$K$5572) -> 835816 | D32: =SUMIF(Levantamento!$E$2:$E$5572,B32,Levantamento!$M$2:$M$5572) -> 932210 | E32: =SUMIF(Levantamento!$E$2:$E$5572,B32,Levantamento!$O$2:$O$5572) -> 981401
A33: SC | B33: RM de Joinville (SC) | C33: =SUMIF(Levantamento!$E$2:$E$5572,B33,Levantamento!$K$2:$K$5572)+SUMIF(Levantamento!$E$2:$E$5572,"RM do Norte/Nordeste Catarinense (SC); RM de Joinville (SC)",Levantamento!$K$2:$K$5572) -> 746967 | D33: =SUMIF(Levantamento!$E$2:$E$5572,B33,Levantamento!$M$2:$M$5572)+SUMIF(Levantamento!$E$2:$E$5572,"RM do Norte/Nordeste Catarinense (SC); RM de Joinville (SC)",Levantamento!$M$2:$M$5572) -> 913520 | E33: =SUMIF(Levantamento!$E$2:$E$5572,B33,Levantamento!$O$2:$O$5572)+SUMIF(Levantamento!$E$2:$E$5572,"RM do Norte/Nordeste Catarinense (SC); RM de Joinville (SC)",Levantamento!$O$2:$O$5572) -> 986981
A34: PR | B34: RM de Maringá (PR) | C34: =SUMIF(Levantamento!$E$2:$E$5572,B34,Levantamento!$K$2:$K$5572) -> 716918 | D34: =SUMIF(Levantamento!$E$2:$E$5572,B34,Levantamento!$M$2:$M$5572) -> 851829 | E34: =SUMIF(Levantamento!$E$2:$E$5572,B34,Levantamento!$O$2:$O$5572) -> 896763
A35: SP | B35: RM de Jundiaí (SP) | C35: =SUMIF(Levantamento!$E$2:$E$5572,B35,Levantamento!$K$2:$K$5572) -> 698724 | D35: =SUMIF(Levantamento!$E$2:$E$5572,B35,Levantamento!$M$2:$M$5572) -> 843633 | E35: =SUMIF(Levantamento!$E$2:$E$5572,B35,Levantamento!$O$2:$O$5572) -> 880995
A36: SC | B36: RM do Vale Europeu (SC) | C36: =SUMIF(Levantamento!$E$2:$E$5572,B36,Levantamento!$K$2:$K$5572) -> 689731 | D36: =SUMIF(Levantamento!$E$2:$E$5572,B36,Levantamento!$M$2:$M$5572) -> 841698 | E36: =SUMIF(Levantamento!$E$2:$E$5572,B36,Levantamento!$O$2:$O$5572) -> 905047
A37: BA_PE | B37: RIDE do Polo Petrolina/PE e Juazeiro/BA | C37: =SUMIF(Levantamento!$E$2:$E$5572,B37,Levantamento!$K$2:$K$5572) -> 686410 | D37: =SUMIF(Levantamento!$E$2:$E$5572,B37,Levantamento!$M$2:$M$5572) -> 834632 | E37: =SUMIF(Levantamento!$E$2:$E$5572,B37,Levantamento!$O$2:$O$5572) -> 895783
A38: RS | B38: RM da Serra Gaúcha (RS) | C38: =SUMIF(Levantamento!$E$2:$E$5572,B38,Levantamento!$K$2:$K$5572) -> 738619 | D38: =SUMIF(Levantamento!$E$2:$E$5572,B38,Levantamento!$M$2:$M$5572) -> 804707 | E38: =SUMIF(Levantamento!$E$2:$E$5572,B38,Levantamento!$O$2:$O$5572) -> 832518
A39: SC | B39: RM da Foz do Rio Itajaí (SC) | C39: =SUMIF(Levantamento!$E$2:$E$5572,B39,Levantamento!$K$2:$K$5572) -> 532771 | D39: =SUMIF(Levantamento!$E$2:$E$5572,B39,Levantamento!$M$2:$M$5572) -> 782160 | E39: =SUMIF(Levantamento!$E$2:$E$5572,B39,Levantamento!$O$2:$O$5572) -> 873893
A40: BA | B40: RM de Feira de Santana (BA) | C40: =SUMIF(Levantamento!$E$2:$E$5572,B40,Levantamento!$K$2:$K$5572) -> 673637 | D40: =SUMIF(Levantamento!$E$2:$E$5572,B40,Levantamento!$M$2:$M$5572) -> 743748 | E40: =SUMIF(Levantamento!$E$2:$E$5572,B40,Levantamento!$O$2:$O$5572) -> 794949
A41: MA | B41: RM do Sudoeste Maranhense (MA) | C41: =SUMIF(Levantamento!$E$2:$E$5572,B41,Levantamento!$K$2:$K$5572) -> 689375 | D41: =SUMIF(Levantamento!$E$2:$E$5572,B41,Levantamento!$M$2:$M$5572) -> 714256 | E41: =SUMIF(Levantamento!$E$2:$E$5572,B41,Levantamento!$O$2:$O$5572) -> 740350
A42: PB | B42: RM de Campina Grande (PB) | C42: =SUMIF(Levantamento!$E$2:$E$5572,B42,Levantamento!$K$2:$K$5572) -> 606047 | D42: =SUMIF(Levantamento!$E$2:$E$5572,B42,Levantamento!$M$2:$M$5572) -> 651619 | E42: =SUMIF(Levantamento!$E$2:$E$5572,B42,Levantamento!$O$2:$O$5572) -> 685664
A43: SC | B43: RM Carbonífera (SC) | C43: =SUMIF(Levantamento!$E$2:$E$5572,B43,Levantamento!$K$2:$K$5572) -> 550206 | D43: =SUMIF(Levantamento!$E$2:$E$5572,B43,Levantamento!$M$2:$M$5572) -> 645359 | E43: =SUMIF(Levantamento!$E$2:$E$5572,B43,Levantamento!$O$2:$O$5572) -> 687399
A44: SP | B44: AU de Franca (SP) | C44: =SUMIF(Levantamento!$E$2:$E$5572,B44,Levantamento!$K$2:$K$5572) -> 600929 | D44: =SUMIF(Levantamento!$E$2:$E$5572,B44,Levantamento!$M$2:$M$5572) -> 638071 | E44: =SUMIF(Levantamento!$E$2:$E$5572,B44,Levantamento!$O$2:$O$5572) -> 657168
A45: CE | B45: RM do Cariri (CE) | C45: =SUMIF(Levantamento!$E$2:$E$5572,B45,Levantamento!$K$2:$K$5572) -> 564478 | D45: =SUMIF(Levantamento!$E$2:$E$5572,B45,Levantamento!$M$2:$M$5572) -> 633326 | E45: =SUMIF(Levantamento!$E$2:$E$5572,B45,Levantamento!$O$2:$O$5572) -> 673263
... A50: PR | B50: RM de Cascavel (PR) | C50: =SUMIF(Levantamento!$E$2:$E$5572,B50,Levantamento!$K$2:$K$5572) -> 488181 | D50: =SUMIF(Levantamento!$E$2:$E$5572,B50,Levantamento!$M$2:$M$5572) -> 559732 | E50: =SUMIF(Levantamento!$E$2:$E$5572,B50,Levantamento!$O$2:$O$5572) -> 584804
A51: MA | B51: RM da Zona Leste do Estado do Maranhão (MA) | C51: =SUMIF(Levantamento!$E$2:$E$5572,B51,Levantamento!$K$2:$K$5572)+SUMIF(Levantamento!$E$2:$E$5572,"RIDE da Grande Teresina (PI/MA); RM da Zona Leste do Estado do Maranhão (MA)",Levantamento!$K$2:$K$5572) -> 535418 | D51: =SUMIF(Levantamento!$E$2:$E$5572,B51,Levantamento!$M$2:$M$5572)+SUMIF(Levantamento!$E$2:$E$5572,"RIDE da Grande Teresina (PI/MA); RM da Zona Leste do Estado do Maranhão (MA)",Levantamento!$M$2:$M$5572) -> 549312 | E51: =SUMIF(Levantamento!$E$2:$E$5572,B51,Levantamento!$O$2:$O$5572)+SUMIF(Levantamento!$E$2:$E$5572,"RIDE da Grande Teresina (PI/MA); RM da Zona Leste do Estado do Maranhão (MA)",Levantamento!$O$2:$O$5572) -> 571128
A52: SC | B52: RM do Contestado (SC) | C52: =SUMIF(Levantamento!$E$2:$E$5572,B52,Levantamento!$K$2:$K$5572) -> 500298 | D52: =SUMIF(Levantamento!$E$2:$E$5572,B52,Levantamento!$M$2:$M$5572) -> 539288 | E52: =SUMIF(Levantamento!$E$2:$E$5572,B52,Levantamento!$O$2:$O$5572) -> 561788
A53: SC | B53: RM de Chapecó (SC) | C53: =SUMIF(Levantamento!$E$2:$E$5572,B53,Levantamento!$K$2:$K$5572) -> 433790 | D53: =SUMIF(Levantamento!$E$2:$E$5572,B53,Levantamento!$M$2:$M$5572) -> 535246 | E53: =SUMIF(Levantamento!$E$2:$E$5572,B53,Levantamento!$O$2:$O$5572) -> 576991
A54: TO | B54: RM de Palmas (TO) | C54: =SUMIF(Levantamento!$E$2:$E$5572,B54,Levantamento!$K$2:$K$5572) -> 400092 | D54: =SUMIF(Levantamento!$E$2:$E$5572,B54,Levantamento!$M$2:$M$5572) -> 495196 | E54: =SUMIF(Levantamento!$E$2:$E$5572,B54,Levantamento!$O$2:$O$5572) -> 531139
A55: RR | B55: RM da Capital (Boa Vista/RR) | C55: =SUMIF(Levantamento!$E$2:$E$5572,B55,Levantamento!$K$2:$K$5572) -> 340398 | D55: =SUMIF(Levantamento!$E$2:$E$5572,B55,Levantamento!$M$2:$M$5572) -> 485282 | E55: =SUMIF(Levantamento!$E$2:$E$5572,B55,Levantamento!$O$2:$O$5572) -> 565744
A56: CE | B56: RM de Sobral (CE) | C56: =SUMIF(Levantamento!$E$2:$E$5572,B56,Levantamento!$K$2:$K$5572) -> 460463 | D56: =SUMIF(Levantamento!$E$2:$E$5572,B56,Levantamento!$M$2:$M$5572) -> 483674 | E56: =SUMIF(Levantamento!$E$2:$E$5572,B56,Levantamento!$O$2:$O$5572) -> 508168
A57: RO | B57: RM de Porto Velho (RO) | C57: =SUMIF(Levantamento!$E$2:$E$5572,B57,Levantamento!$K$2:$K$5572) -> 448306 | D57: =SUMIF(Levantamento!$E$2:$E$5572,B57,Levantamento!$M$2:$M$5572) -> 482744 | E57: =SUMIF(Levantamento!$E$2:$E$5572,B57,Levantamento!$O$2:$O$5572) -> 542022
A58: MG | B58: RM do Vale do Aço (MG) | C58: =SUMIF(Levantamento!$E$2:$E$5572,B58,Levantamento!$K$2:$K$5572) -> 451670 | D58: =SUMIF(Levantamento!$E$2:$E$5572,B58,Levantamento!$M$2:$M$5572) -> 458846 | E58: =SUMIF(Levantamento!$E$2:$E$5572,B58,Levantamento!$O$2:$O$5572) -> 477216
A59: PR | B59: RM de Toledo (PR) | C59: =SUMIF(Levantamento!$E$2:$E$5572,B59,Levantamento!$K$2:$K$5572) -> 358660 | D59: =SUMIF(Levantamento!$E$2:$E$5572,B59,Levantamento!$M$2:$M$5572) -> 418589 | E59: =SUMIF(Levantamento!$E$2:$E$5572,B59,Levantamento!$O$2:$O$5572) -> 439615
A60: SC | B60: RM de Tubarão (SC) | C60: =SUMIF(Levantamento!$E$2:$E$5572,B60,Levantamento!$K$2:$K$5572) -> 356721 | D60: =SUMIF(Levantamento!$E$2:$E$5572,B60,Levantamento!$M$2:$M$5572) -> 405191 | E60: =SUMIF(Levantamento!$E$2:$E$5572,B60,Levantamento!$O$2:$O$5572) -> 427836
A61: PA | B61: RM de Santarém (PA) | C61: =SUMIF(Levantamento!$E$2:$E$5572,B61,Levantamento!$K$2:$K$5572) -> 310898 | D61: =SUMIF(Levantamento!$E$2:$E$5572,B61,Levantamento!$M$2:$M$5572) -> 373542 | E61: =SUMIF(Levantamento!$E$2:$E$5572,B61,Levantamento!$O$2:$O$5572) -> 405764
A62: SC | B62: RM de Lages (SC) | C62: =SUMIF(Levantamento!$E$2:$E$5572,B62,Levantamento!$K$2:$K$5572) -> 350532 | D62: =SUMIF(Levantamento!$E$2:$E$5572,B62,Levantamento!$M$2:$M$5572) -> 362506 | E62: =SUMIF(Levantamento!$E$2:$E$5572,B62,Levantamento!$O$2:$O$5572) -> 375095
A63: RS | B63: AU do Litoral Norte (RS) | C63: =SUMIF(Levantamento!$E$2:$E$5572,B63,Levantamento!$K$2:$K$5572) -> 283959 | D63: =SUMIF(Levantamento!$E$2:$E$5572,B63,Levantamento!$M$2:$M$5572) -> 360603 | E63: =SUMIF(Levantamento!$E$2:$E$5572,B63,Levantamento!$O$2:$O$5572) -> 373075
... A65: PR | B65: RM de Campo Mourão (PR) | C65: =SUMIF(Levantamento!$E$2:$E$5572,B65,Levantamento!$K$2:$K$5572) -> 334125 | D65: =SUMIF(Levantamento!$E$2:$E$5572,B65,Levantamento!$M$2:$M$5572) -> 341931 | E65: =SUMIF(Levantamento!$E$2:$E$5572,B65,Levantamento!$O$2:$O$5572) -> 349296
A66: SC | B66: RM de Jaraguá do Sul (SC) | C66: =SUMIF(Levantamento!$E$2:$E$5572,B66,Levantamento!$K$2:$K$5572)+SUMIF(Levantamento!$E$2:$E$5572,"RM do Norte/Nordeste Catarinense (SC); RM de Jaraguá do Sul (SC)",Levantamento!$K$2:$K$5572) -> 247958 | D66: =SUMIF(Levantamento!$E$2:$E$5572,B66,Levantamento!$M$2:$M$5572)+SUMIF(Levantamento!$E$2:$E$5572,"RM do Norte/Nordeste Catarinense (SC); RM de Jaraguá do Sul (SC)",Levantamento!$M$2:$M$5572) -> 331693 | E66: =SUMIF(Levantamento!$E$2:$E$5572,B66,Levantamento!$O$2:$O$5572)+SUMIF(Levantamento!$E$2:$E$5572,"RM do Norte/Nordeste Catarinense (SC); RM de Jaraguá do Sul (SC)",Levantamento!$O$2:$O$5572) -> 363959
A67: PR | B67: RM de Umuarama (PR) | C67: =SUMIF(Levantamento!$E$2:$E$5572,B67,Levantamento!$K$2:$K$5572) -> 299447 | D67: =SUMIF(Levantamento!$E$2:$E$5572,B67,Levantamento!$M$2:$M$5572) -> 325387 | E67: =SUMIF(Levantamento!$E$2:$E$5572,B67,Levantamento!$O$2:$O$5572) -> 336162
A68: SC | B68: RM do Alto Vale do Itajaí (SC) | C68: =SUMIF(Levantamento!$E$2:$E$5572,B68,Levantamento!$K$2:$K$5572) -> 269424 | D68: =SUMIF(Levantamento!$E$2:$E$5572,B68,Levantamento!$M$2:$M$5572) -> 309808 | E68: =SUMIF(Levantamento!$E$2:$E$5572,B68,Levantamento!$O$2:$O$5572) -> 327120
A69: PR | B69: RM de Apucarana (PR) | C69: =SUMIF(Levantamento!$E$2:$E$5572,B69,Levantamento!$K$2:$K$5572) -> 289457 | D69: =SUMIF(Levantamento!$E$2:$E$5572,B69,Levantamento!$M$2:$M$5572) -> 296131 | E69: =SUMIF(Levantamento!$E$2:$E$5572,B69,Levantamento!$O$2:$O$5572) -> 302889
A70: MG | B70: Colar Metropolitano do Vale do Aço (MG) | C70: =SUMIF(Levantamento!$E$2:$E$5572,B70,Levantamento!$K$2:$K$5572) -> 264230 | D70: =SUMIF(Levantamento!$E$2:$E$5572,B70,Levantamento!$M$2:$M$5572) -> 259437 | E70: =SUMIF(Levantamento!$E$2:$E$5572,B70,Levantamento!$O$2:$O$5572) -> 265740
A71: PB | B71: RM de Guarabira (PB) | C71: =SUMIF(Levantamento!$E$2:$E$5572,B71,Levantamento!$K$2:$K$5572) -> 244351 | D71: =SUMIF(Levantamento!$E$2:$E$5572,B71,Levantamento!$M$2:$M$5572) -> 243173 | E71: =SUMIF(Levantamento!$E$2:$E$5572,B71,Levantamento!$O$2:$O$5572) -> 250686
A72: SC | B72: RM do Planalto Norte (SC) | C72: =SUMIF(Levantamento!$E$2:$E$5572,B72,Levantamento!$K$2:$K$5572)+SUMIF(Levantamento!$E$2:$E$5572,"RM do Norte/Nordeste Catarinense (SC); RM do Planalto Norte (SC)",Levantamento!$K$2:$K$5572) -> 227805 | D72: =SUMIF(Levantamento!$E$2:$E$5572,B72,Levantamento!$M$2:$M$5572)+SUMIF(Levantamento!$E$2:$E$5572,"RM do Norte/Nordeste Catarinense (SC); RM do Planalto Norte (SC)",Levantamento!$M$2:$M$5572) -> 235537 | E72: =SUMIF(Levantamento!$E$2:$E$5572,B72,Levantamento!$O$2:$O$5572)+SUMIF(Levantamento!$E$2:$E$5572,"RM do Norte/Nordeste Catarinense (SC); RM do Planalto Norte (SC)",Levantamento!$O$2:$O$5572) -> 242760
A73: PB | B73: RM de Patos (PB) | C73: =SUMIF(Levantamento!$E$2:$E$5572,B73,Levantamento!$K$2:$K$5572) -> 219738 | D73: =SUMIF(Levantamento!$E$2:$E$5572,B73,Levantamento!$M$2:$M$5572) -> 222863 | E73: =SUMIF(Levantamento!$E$2:$E$5572,B73,Levantamento!$O$2:$O$5572) -> 231301
A74: PI | B74: RM de Parnaíba (PI) | C74: =SUMIF(Levantamento!$E$2:$E$5572,B74,Levantamento!$K$2:$K$5572) -> 190188 | D74: =SUMIF(Levantamento!$E$2:$E$5572,B74,Levantamento!$M$2:$M$5572) -> 210031 | E74: =SUMIF(Levantamento!$E$2:$E$5572,B74,Levantamento!$O$2:$O$5572) -> 220160
A75: TO | B75: RM de Gurupi (TO) | C75: =SUMIF(Levantamento!$E$2:$E$5572,B75,Levantamento!$K$2:$K$5572) -> 179628 | D75: =SUMIF(Levantamento!$E$2:$E$5572,B75,Levantamento!$M$2:$M$5572) -> 190501 | E75: =SUMIF(Levantamento!$E$2:$E$5572,B75,Levantamento!$O$2:$O$5572) -> 198965
A76: BA | B76: Área de Expansão Metropolitana de Feira de Santana (BA) | C76: =SUMIF(Levantamento!$E$2:$E$5572,B76,Levantamento!$K$2:$K$5572) -> 172302 | D76: =SUMIF(Levantamento!$E$2:$E$5572,B76,Levantamento!$M$2:$M$5572) -> 179443 | E76: =SUMIF(Levantamento!$E$2:$E$5572,B76,Levantamento!$O$2:$O$5572) -> 187688
A77: PB | B77: RM de Cajazeiras (PB) | C77: =SUMIF(Levantamento!$E$2:$E$5572,B77,Levantamento!$K$2:$K$5572) -> 167971 | D77: =SUMIF(Levantamento!$E$2:$E$5572,B77,Levantamento!$M$2:$M$5572) -> 173175 | E77: =SUMIF(Levantamento!$E$2:$E$5572,B77,Levantamento!$O$2:$O$5572) -> 179649
A78: PB | B78: RM de Esperança (PB) | C78: =SUMIF(Levantamento!$E$2:$E$5572,B78,Levantamento!$K$2:$K$5572) -> 134085 | D78: =SUMIF(Levantamento!$E$2:$E$5572,B78,Levantamento!$M$2:$M$5572) -> 137164 | E78: =SUMIF(Levantamento!$E$2:$E$5572,B78,Levantamento!$O$2:$O$5572) -> 141998
A79: PB | B79: RM do Vale do Piancó (PB) | C79: =SUMIF(Levantamento!$E$2:$E$5572,B79,Levantamento!$K$2:$K$5572) -> 140761 | D79: =SUMIF(Levantamento!$E$2:$E$5572,B79,Levantamento!$M$2:$M$5572) -> 136464 | E79: =SUMIF(Levantamento!$E$2:$E$5572,B79,Levantamento!$O$2:$O$5572) -> 139447
A80: PB | B80: RM de Itabaiana (PB) | C80: =SUMIF(Levantamento!$E$2:$E$5572,B80,Levantamento!$K$2:$K$5572) -> 131992 | D80: =SUMIF(Levantamento!$E$2:$E$5572,B80,Levantamento!$M$2:$M$5572) -> 133563 | E80: =SUMIF(Levantamento!$E$2:$E$5572,B80,Levantamento!$O$2:$O$5572) -> 137638
A81: MA | B81: RM da Grande Pedreiras (MA) | C81: =SUMIF(Levantamento!$E$2:$E$5572,B81,Levantamento!$K$2:$K$5572) -> 129796 | D81: =SUMIF(Levantamento!$E$2:$E$5572,B81,Levantamento!$M$2:$M$5572) -> 127745 | E81: =SUMIF(Levantamento!$E$2:$E$5572,B81,Levantamento!$O$2:$O$5572) -> 130941
A82: PB | B82: RM do Vale do Mamanguape (PB) | C82: =SUMIF(Levantamento!$E$2:$E$5572,B82,Levantamento!$K$2:$K$5572) -> 113446 | D82: =SUMIF(Levantamento!$E$2:$E$5572,B82,Levantamento!$M$2:$M$5572) -> 121196 | E82: =SUMIF(Levantamento!$E$2:$E$5572,B82,Levantamento!$O$2:$O$5572) -> 126816
A83: PB | B83: RM de Sousa (PB) | C83: =SUMIF(Levantamento!$E$2:$E$5572,B83,Levantamento!$K$2:$K$5572) -> 112217 | D83: =SUMIF(Levantamento!$E$2:$E$5572,B83,Levantamento!$M$2:$M$5572) -> 113363 | E83: =SUMIF(Levantamento!$E$2:$E$5572,B83,Levantamento!$O$2:$O$5572) -> 117441
A84: MT | B84: Entorno Metropolitano da RM do Vale do Rio Cuiabá (MT) | C84: =SUMIF(Levantamento!$E$2:$E$5572,B84,Levantamento!$K$2:$K$5572) -> 87060 | D84: =SUMIF(Levantamento!$E$2:$E$5572,B84,Levantamento!$M$2:$M$5572) -> 83939 | E84: =SUMIF(Levantamento!$E$2:$E$5572,B84,Levantamento!$O$2:$O$5572) -> 83709
... A88: RR | B88: RM de Central (RR) | C88: =SUMIF(Levantamento!$E$2:$E$5572,B88,Levantamento!$K$2:$K$5572) -> 27094 | D88: =SUMIF(Levantamento!$E$2:$E$5572,B88,Levantamento!$M$2:$M$5572) -> 30980 | E88: =SUMIF(Levantamento!$E$2:$E$5572,B88,Levantamento!$O$2:$O$5572) -> 33687

Sheet Resumo
B1: Censo 2022
A2: Obrigados a elaborar o plano | B2: =COUNTIF(Levantamento!AH1:AH5572,"Sim") -> 1910
A3: Obrigados que prestaram informações | B3: =COUNTIFS(Levantamento!AH1:AH5572,"Sim",Levantamento!R1:R5572,"Sim") -> 1441 | C3: =B3/B2 -> 0.75445026
A4: Municípios que possuem plano | B4: =COUNTIF(Levantamento!S1:S5572,"Sim") -> 486
A5: Obrigados que possuem plano | B5: =COUNTIFS(Levantamento!AH1:AH5572,"Sim",Levantamento!S1:S5572,"Sim") -> 466 | C5: =B5/B2 -> 0.24397906
A6: Mais de 250 mil habitantes que possuem plano | B6: =COUNTIFS(Levantamento!N1:N5572,"Mais de 1 milhão", Levantamento!S1:S5572,"Sim")+COUNTIFS(Levantamento!N1:N5572,"De 500 mil a 1 milhão", Levantamento!S1:S5572,"Sim")+COUNTIFS(Levantamento!N1:N5572,"De 250 mil a 500 mil", Levantamento!S1:S5572,"Sim") -> 100 | C6: =B6/COUNTIF(Levantamento!M1:M5572,">=250000") -> 0.86206897
A7: Municípios com plano aprovado em instrumento normativo | B7: =COUNTIF(Levantamento!U1:U5572,"Sim") -> 407
A8: Obrigados com plano aprovado em instrumento normativo | B8: =COUNTIFS(Levantamento!AH1:AH5572,"Sim",Levantamento!U1:U5572,"Sim") -> 393 | C8: =B8/B2 -> 0.20575916
A9: Mais de 250 mil hab. com plano aprovado em instrumento normativo | B9: =COUNTIFS(Levantamento!N1:N5572,"Mais de 1 milhão", Levantamento!U1:U5572,"Sim")+COUNTIFS(Levantamento!N1:N5572,"De 500 mil a 1 milhão", Levantamento!U1:U5572,"Sim")+COUNTIFS(Levantamento!N1:N5572,"De 250 mil a 500 mil", Levantamento!U1:U5572,"Sim") -> 90 | C9: =B9/COUNTIF(Levantamento!M1:M5572,">=250000") -> 0.77586207
A11: N | E11: =COUNTIFS(Levantamento!$B$1:$B$5572,"N",Levantamento!$U$1:$U$5572,"Sim",Levantamento!$AI$1:$AI$5572,"Sim") -> 37 | F11: =COUNTIFS(Levantamento!$B$1:$B$5572,"N",Levantamento!$AI$1:$AI$5572,"Sim") -> 187 | H11: =E11/F11 -> 0.19786096
A12: NE | E12: =COUNTIFS(Levantamento!$B$1:$B$5572,"NE",Levantamento!$U$1:$U$5572,"Sim",Levantamento!$AI$1:$AI$5572,"Sim") -> 41 | F12: =COUNTIFS(Levantamento!$B$1:$B$5572,"NE",Levantamento!$AI$1:$AI$5572,"Sim") -> 623 | H12: =E12/F12 -> 0.065810594
A13: CO | E13: =COUNTIFS(Levantamento!$B$1:$B$5572,"CO",Levantamento!$U$1:$U$5572,"Sim",Levantamento!$AI$1:$AI$5572,"Sim") -> 26 | F13: =COUNTIFS(Levantamento!$B$1:$B$5572,"CO",Levantamento!$AI$1:$AI$5572,"Sim") -> 154 | H13: =E13/F13 -> 0.16883117
A14: SE | E14: =COUNTIFS(Levantamento!$B$1:$B$5572,"SE",Levantamento!$U$1:$U$5572,"Sim",Levantamento!$AI$1:$AI$5572,"Sim") -> 191 | F14: =COUNTIFS(Levantamento!$B$1:$B$5572,"SE",Levantamento!$AI$1:$AI$5572,"Sim") -> 613 | H14: =E14/F14 -> 0.31158238
A15: S | E15: =COUNTIFS(Levantamento!$B$1:$B$5572,"S",Levantamento!$U$1:$U$5572,"Sim",Levantamento!$AI$1:$AI$5572,"Sim") -> 98 | F15: =COUNTIFS(Levantamento!$B$1:$B$5572,"S",Levantamento!$AI$1:$AI$5572,"Sim") -> 333 | H15: =E15/F15 -> 0.29429429
B17: Estimativa 2025
A18: Obrigados a elaborar o plano | B18: =COUNTIF(Levantamento!AG1:AG5572,"Sim") -> 1979
A19: Obrigados que prestaram informações | B19: =COUNTIFS(Levantamento!AG1:AG5572,"Sim",Levantamento!R1:R5572,"Sim") -> 1464 | C19: =B19/B18 -> 0.73976756
A20: Municípios que possuem plano | B20: =COUNTIF(Levantamento!S1:S5572,"Sim") -> 486
A21: Obrigados que possuem plano | B21: =COUNTIFS(Levantamento!AG1:AG5572,"Sim",Levantamento!S1:S5572,"Sim") -> 468 | C21: =B21/B18 -> 0.23648307
A22: Mais de 250 mil habitantes que possuem plano | B22: =COUNTIFS(Levantamento!P1:P5572,"Mais de 1 milhão", Levantamento!S1:S5572,"Sim")+COUNTIFS(Levantamento!P1:P5572,"De 500 mil a 1 milhão", Levantamento!S1:S5572,"Sim")+COUNTIFS(Levantamento!P1:P5572,"De 250 mil a 500 mil", Levantamento!S1:S5572,"Sim") -> 103 | C22: =B22/COUNTIF(Levantamento!O1:O5572,">=250000") -> 0.824
A23: Municípios com plano aprovado em instrumento normativo | B23: =COUNTIF(Levantamento!U1:U5572,"Sim") -> 407
A24: Obrigados com plano aprovado em instrumento normativo | B24: =COUNTIFS(Levantamento!AG1:AG5572,"Sim",Levantamento!U1:U5572,"Sim") -> 394 | C24: =B24/B18 -> 0.19909045
A25: Mais de 250 mil hab. com plano aprovado em instrumento normativo | B25: =COUNTIFS(Levantamento!P1:P5572,"Mais de 1 milhão", Levantamento!U1:U5572,"Sim")+COUNTIFS(Levantamento!P1:P5572,"De 500 mil a 1 milhão", Levantamento!U1:U5572,"Sim")+COUNTIFS(Levantamento!P1:P5572,"De 250 mil a 500 mil", Levantamento!U1:U5572,"Sim") -> 92 | C25: =B25/COUNTIF(Levantamento!O1:O5572,">=250000") -> 0.736
